Workbook

Sheet Dashboard
A1: USD/KRW Monitor
A2: ="As of "&TEXT(B4,"d mmm yyyy")&" | Fed H.10, FRED, BOK ECOS, KRX"
A3: Observations (daily) | B3: =COUNT(Daily!$B:$B)
A4: Last fixing | B4: =INDEX(Daily!$A:$A,$B$3+1)
A5: USD/KRW spot | B5: =INDEX(Daily!$B:$B,$B$3+1)
A7: Spot performance (+ = weaker KRW) | G7: Asia FX and risk context
A8: Period | B8: Level then | C8: Change | G8: Measure | H8: Value | I8: 1M change
A9: 1 day | B9: =INDEX(Daily!$B:$B,$B$3+1-Inputs!$B$19) | C9: =$B$5/B9-1 | G9: USD/JPY | H9: =IFERROR(LOOKUP(2,1/(Daily!$E$2:$E$7964<>""),Daily!$E$2:$E$7964),"n/a") | I9: =IFERROR(H9/INDEX(Daily!$E:$E,$B$3+1-21)-1,"n/a")
A10: 1 week | B10: =INDEX(Daily!$B:$B,$B$3+1-Inputs!$B$20) | C10: =$B$5/B10-1 | G10: USD/CNY | H10: =IFERROR(LOOKUP(2,1/(Daily!$G$2:$G$7964<>""),Daily!$G$2:$G$7964),"n/a") | I10: =IFERROR(H10/INDEX(Daily!$G:$G,$B$3+1-21)-1,"n/a")
A11: 1 month | B11: =INDEX(Daily!$B:$B,$B$3+1-Inputs!$B$21) | C11: =$B$5/B11-1 | G11: USD broad index | H11: =IFERROR(LOOKUP(2,1/(Daily!$I$2:$I$7964<>""),Daily!$I$2:$I$7964),"n/a")
A12: 3 months | B12: =INDEX(Daily!$B:$B,$B$3+1-Inputs!$B$22) | C12: =$B$5/B12-1 | G12: VIX | H12: =IFERROR(LOOKUP(2,1/(Daily!$J$2:$J$7964<>""),Daily!$J$2:$J$7964),"n/a")
A13: 1 year | B13: =INDEX(Daily!$B:$B,$B$3+1-Inputs!$B$23) | C13: =$B$5/B13-1 | G13: UST 10Y % | H13: =IFERROR(LOOKUP(2,1/(Daily!$K$2:$K$7964<>""),Daily!$K$2:$K$7964),"n/a")
A14: Year to date | B14: =INDEX(Daily!$B:$B,MATCH(DATE(YEAR($B$4)-1,12,31),Daily!$A:$A,1)) | C14: =$B$5/B14-1 | G14: SOFR % | H14: =IFERROR(LOOKUP(2,1/(Daily!$L$2:$L$7964<>""),Daily!$L$2:$L$7964),"n/a")
A16: Realized risk | G16: Correlation with KRW (daily returns)
A17: Measure | B17: Value | G17: Pair | H17: 60 days | I17: 1 year
A18: Realized vol, 20 days (ann.) | B18: =STDEV(INDEX(Daily!$C:$C,$B$3+1-19):INDEX(Daily!$C:$C,$B$3+1))*SQRT(Inputs!$D$10) | G18: KRW vs JPY | H18: =IFERROR(CORREL(INDEX(Daily!$C:$C,$B$3+1-59):INDEX(Daily!$C:$C,$B$3+1),INDEX(Daily!$F:$F,$B$3+1-59):INDEX(Daily!$F:$F,$B$3+1)),"n/a") | I18: =IFERROR(CORREL(INDEX(Daily!$C:$C,$B$3+1-251):INDEX(Daily!$C:$C,$B$3+1),INDEX(Daily!$F:$F,$B$3+1-251):INDEX(Daily!$F:$F,$B$3+1)),"n/a")
A19: Realized vol, 60 days (ann.) | B19: =STDEV(INDEX(Daily!$C:$C,$B$3+1-59):INDEX(Daily!$C:$C,$B$3+1))*SQRT(Inputs!$D$10) | G19: KRW vs CNY | H19: =IFERROR(CORREL(INDEX(Daily!$C:$C,$B$3+1-59):INDEX(Daily!$C:$C,$B$3+1),INDEX(Daily!$H:$H,$B$3+1-59):INDEX(Daily!$H:$H,$B$3+1)),"n/a") | I19: =IFERROR(CORREL(INDEX(Daily!$C:$C,$B$3+1-251):INDEX(Daily!$C:$C,$B$3+1),INDEX(Daily!$H:$H,$B$3+1-251):INDEX(Daily!$H:$H,$B$3+1)),"n/a")
A20: Realized vol, 1 year (ann.) | B20: =STDEV(INDEX(Daily!$C:$C,$B$3+1-251):INDEX(Daily!$C:$C,$B$3+1))*SQRT(Inputs!$D$10) | G20: Beta of KRW to JPY (1 year) | H20: =IFERROR(SLOPE(INDEX(Daily!$C:$C,$B$3+1-251):INDEX(Daily!$C:$C,$B$3+1),INDEX(Daily!$F:$F,$B$3+1-251):INDEX(Daily!$F:$F,$B$3+1)),"n/a")
A21: 1-year high | B21: =MAX(INDEX(Daily!$B:$B,$B$3+1-251):INDEX(Daily!$B:$B,$B$3+1))
A22: 1-year low | B22: =MIN(INDEX(Daily!$B:$B,$B$3+1-251):INDEX(Daily!$B:$B,$B$3+1)) | G22: Rate gap, KRW minus USD (pts) | H22: =(B28-D28)*100
A23: Position in 1-year range | B23: =IFERROR(($B$5-B22)/(B21-B22),"")
A24: Z-score vs. 1-year mean | B24: =($B$5-AVERAGE(INDEX(Daily!$B:$B,$B$3+1-251):INDEX(Daily!$B:$B,$B$3+1)))/STDEV(INDEX(Daily!$B:$B,$B$3+1-251):INDEX(Daily!$B:$B,$B$3+1)) | G24: Dollar supply and demand (US$ mn)
A25: Largest 1-day move, last year | B25: =MAX(MAX(INDEX(Daily!$C:$C,$B$3+1-251):INDEX(Daily!$C:$C,$B$3+1)),-MIN(INDEX(Daily!$C:$C,$B$3+1-251):INDEX(Daily!$C:$C,$B$3+1))) | G25: Measure | H25: Value
G26: Latest balance-of-payments month | H26: =IFERROR(LOOKUP(2,1/(Flows_Monthly!$B$5:$B$386<>""),Flows_Monthly!$A$5:$A$386),"n/a")
A27: Implied forwards (CIP) | G27: Current account, that month | H27: =IFERROR(INDEX(Flows_Monthly!$B$5:$B$386,MATCH($H$26,Flows_Monthly!$A$5:$A$386,0)),"n/a")
A28: KRW rate used | B28: =Inputs!D5 | C28: USD rate used | D28: =Inputs!D6 | G28: Basic balance, that month | H28: =IFERROR(INDEX(Flows_Monthly!$J$5:$J$386,MATCH($H$26,Flows_Monthly!$A$5:$A$386,0)),"n/a")
A29: Tenor | B29: Days | C29: Forward | D29: Swap points (won) | E29: Hedge carry (ann.) | G29: Current account, 12M | H29: =IFERROR(INDEX(Flows_Monthly!$Q$5:$Q$386,MATCH($H$26,Flows_Monthly!$A$5:$A$386,0)),"n/a")
A30: =Inputs!A13 | B30: =Inputs!B13 | C30: =$B$5*(1+$B$28*B30/365)/(1+$D$28*B30/360) | D30: =C30-$B$5 | E30: =(C30/$B$5-1)*365/B30 | G30: Residents' outward investment, 12M | H30: =IFERROR(INDEX(Flows_Monthly!$R$5:$R$386,MATCH($H$26,Flows_Monthly!$A$5:$A$386,0)),"n/a")
A31: =Inputs!A14 | B31: =Inputs!B14 | C31: =$B$5*(1+$B$28*B31/365)/(1+$D$28*B31/360) | D31: =C31-$B$5 | E31: =(C31/$B$5-1)*365/B31 | G31: Foreigners' inward investment, 12M | H31: =IFERROR(INDEX(Flows_Monthly!$S$5:$S$386,MATCH($H$26,Flows_Monthly!$A$5:$A$386,0)),"n/a")
A32: =Inputs!A15 | B32: =Inputs!B15 | C32: =$B$5*(1+$B$28*B32/365)/(1+$D$28*B32/360) | D32: =C32-$B$5 | E32: =(C32/$B$5-1)*365/B32 | G32: Basic balance, 12M | H32: =IFERROR(INDEX(Flows_Monthly!$T$5:$T$386,MATCH($H$26,Flows_Monthly!$A$5:$A$386,0)),"n/a")
A33: =Inputs!A16 | B33: =Inputs!B16 | C33: =$B$5*(1+$B$28*B33/365)/(1+$D$28*B33/360) | D33: =C33-$B$5 | E33: =(C33/$B$5-1)*365/B33 | G33: Foreign equity net buying, 5D (KRW bn) | H33: =IF(COUNT(Flows_Daily!$A:$A)+1<6,"n/a",SUM(INDEX(Flows_Daily!$D:$D,COUNT(Flows_Daily!$A:$A)+1-4):INDEX(Flows_Daily!$D:$D,COUNT(Flows_Daily!$A:$A)+1)))
A34: 3M points x notional (KRW) | B34: =Inputs!D9*D31 | G34: Foreign equity net buying, 20D (KRW bn) | H34: =IF(COUNT(Flows_Daily!$A:$A)+1<21,"n/a",SUM(INDEX(Flows_Daily!$D:$D,COUNT(Flows_Daily!$A:$A)+1-19):INDEX(Flows_Daily!$D:$D,COUNT(Flows_Daily!$A:$A)+1)))
A35: Rate-implied; excludes the cross-currency basis. | G35: Corr. foreign buying vs KRW return, 1Y | H35: =IFERROR(CORREL(INDEX(Daily!$C:$C,$B$3+1-251):INDEX(Daily!$C:$C,$B$3+1),INDEX(Daily!$O:$O,$B$3+1-251):INDEX(Daily!$O:$O,$B$3+1)),"n/a")
G36: Positive = net dollar supply.

Sheet Charts
A1: USD/KRW chart pack
A2: =Dashboard!A2

Sheet Inputs
A1: Inputs and assumptions
A2: Blue = input. Shaded = override (blank uses latest data).
A4: Item | B4: Latest data | C4: Override | D4: Used | E4: Source / note
A5: KRW rate (ACT/365) | B5: =Rates_Monthly!B380/100 | D5: =IF(C5="",B5,C5) | E5: Latest OECD 3-month rate (monthly). Desks would use CD91 or KRW deposit/KOFR rates: type them in Override.
A6: USD rate (ACT/360) | B6: =Rates_Monthly!C380/100 | D6: =IF(C6="",B6,C6) | E6: Latest OECD 3-month rate (monthly). Override with SOFR term rate if preferred.
A7: Rate data as of | B7: =Rates_Monthly!A380
A9: Hedge notional (USD) | D9: 10000000 | E9: Used for the hedge-cost example on the Dashboard.
A10: Trading days per year | D10: 252 | E10: Annualization for realized volatility.
A12: Forward tenor | B12: Days | E12: Note
A13: 1M | B13: 30 | E13: Calendar days. Edit to match actual value dates.
A14: 3M | B14: 91
A15: 6M | B15: 182
A16: 1Y | B16: 365
A18: Lookback | B18: Trading days | E18: Note
A19: 1 day | B19: 1 | E19: Observations back from the latest fixing.
A20: 1 week | B20: 5
A21: 1 month | B21: 21
A22: 3 months | B22: 63
A23: 1 year | B23: 252

Sheet Daily
A1: Date | B1: USD/KRW | C1: KRW log return | D1: KRW 20D vol (ann.) | E1: USD/JPY | F1: JPY log return | G1: USD/CNY | H1: CNY log return | I1: USD broad index | J1: VIX | K1: UST 10Y % | L1: SOFR % | M1: BOK USD/KRW | N1: CD 91D % | O1: Foreign net buy (KRW bn)
A2: 34702 | B2: 791.8 | E2: 100.52 | G2: 8.4647 | J2: 14.25 | K2: 7.88
A3: 34703 | B3: 791.6 | C3: =IF(OR(B3="",B2=""),"",LN(B3/B2)) | E3: 101.4 | F3: =IF(OR(E3="",E2=""),"",LN(E3/E2)) | G3: 8.4647 | H3: =IF(OR(G3="",G2=""),"",LN(G3/G2)) | J3: 13.53 | K3: 7.82
A4: 34704 | B4: 792.4 | C4: =IF(OR(B4="",B3=""),"",LN(B4/B3)) | E4: 100.97 | F4: =IF(OR(E4="",E3=""),"",LN(E4/E3)) | G4: 8.463 | H4: =IF(OR(G4="",G3=""),"",LN(G4/G3)) | J4: 13.5 | K4: 7.88
A5: 34705 | B5: 792.7 | C5: =IF(OR(B5="",B4=""),"",LN(B5/B4)) | E5: 101.37 | F5: =IF(OR(E5="",E4=""),"",LN(E5/E4)) | G5: 8.4626 | H5: =IF(OR(G5="",G4=""),"",LN(G5/G4)) | J5: 13.13 | K5: 7.87
A6: 34708 | B6: 793.4 | C6: =IF(OR(B6="",B5=""),"",LN(B6/B5)) | E6: 100.33 | F6: =IF(OR(E6="",E5=""),"",LN(E6/E5)) | G6: 8.4622 | H6: =IF(OR(G6="",G5=""),"",LN(G6/G5)) | J6: 13.33 | K6: 7.89
A7: 34709 | B7: 794.1 | C7: =IF(OR(B7="",B6=""),"",LN(B7/B6)) | E7: 100.4 | F7: =IF(OR(E7="",E6=""),"",LN(E7/E6)) | G7: 8.4617 | H7: =IF(OR(G7="",G6=""),"",LN(G7/G6)) | J7: 12.52 | K7: 7.84
A8: 34710 | B8: 794.3 | C8: =IF(OR(B8="",B7=""),"",LN(B8/B7)) | E8: 99.9 | F8: =IF(OR(E8="",E7=""),"",LN(E8/E7)) | G8: 8.4615 | H8: =IF(OR(G8="",G7=""),"",LN(G8/G7)) | J8: 12.15 | K8: 7.79
A9: 34711 | B9: 793.3 | C9: =IF(OR(B9="",B8=""),"",LN(B9/B8)) | E9: 98.8 | F9: =IF(OR(E9="",E8=""),"",LN(E9/E8)) | G9: 8.4612 | H9: =IF(OR(G9="",G8=""),"",LN(G9/G8)) | J9: 12.83 | K9: 7.8
A10: 34712 | B10: 793.1 | C10: =IF(OR(B10="",B9=""),"",LN(B10/B9)) | E10: 98.77 | F10: =IF(OR(E10="",E9=""),"",LN(E10/E9)) | G10: 8.4611 | H10: =IF(OR(G10="",G9=""),"",LN(G10/G9)) | J10: 11.1 | K10: 7.69
A11: 34716 | B11: 795.8 | C11: =IF(OR(B11="",B10=""),"",LN(B11/B10)) | E11: 99 | F11: =IF(OR(E11="",E10=""),"",LN(E11/E10)) | G11: 8.4607 | H11: =IF(OR(G11="",G10=""),"",LN(G11/G10)) | J11: 11.79 | K11: 7.7
A12: 34717 | B12: 795.1 | C12: =IF(OR(B12="",B11=""),"",LN(B12/B11)) | E12: 99.55 | F12: =IF(OR(E12="",E11=""),"",LN(E12/E11)) | G12: 8.4605 | H12: =IF(OR(G12="",G11=""),"",LN(G12/G11)) | J12: 11.57 | K12: 7.71
A13: 34718 | B13: 795.6 | C13: =IF(OR(B13="",B12=""),"",LN(B13/B12)) | E13: 99.43 | F13: =IF(OR(E13="",E12=""),"",LN(E13/E12)) | G13: 8.4602 | H13: =IF(OR(G13="",G12=""),"",LN(G13/G12)) | J13: 11.86 | K13: 7.74
A14: 34719 | B14: 795.5 | C14: =IF(OR(B14="",B13=""),"",LN(B14/B13)) | E14: 99.4 | F14: =IF(OR(E14="",E13=""),"",LN(E14/E13)) | G14: 8.46 | H14: =IF(OR(G14="",G13=""),"",LN(G14/G13)) | J14: 12.15 | K14: 7.82
... A21: 34730 | B21: 789.8 | C21: =IF(OR(B21="",B20=""),"",LN(B21/B20)) | E21: 99.43 | F21: =IF(OR(E21="",E20=""),"",LN(E21/E20)) | G21: 8.4584 | H21: =IF(OR(G21="",G20=""),"",LN(G21/G20)) | J21: 11.96 | K21: 7.6
A22: 34731 | B22: 789.8 | C22: =IF(OR(B22="",B21=""),"",LN(B22/B21)) | D22: =STDEV(C3:C22)*SQRT(252) | E22: 99.4 | F22: =IF(OR(E22="",E21=""),"",LN(E22/E21)) | G22: 8.4585 | H22: =IF(OR(G22="",G21=""),"",LN(G22/G21)) | J22: 11.73 | K22: 7.66
A23: 34732 | B23: 789.8 | C23: =IF(OR(B23="",B22=""),"",LN(B23/B22)) | D23: =STDEV(C4:C23)*SQRT(252) | E23: 99.5 | F23: =IF(OR(E23="",E22=""),"",LN(E23/E22)) | G23: 8.4584 | H23: =IF(OR(G23="",G22=""),"",LN(G23/G22)) | J23: 11.13 | K23: 7.68
A24: 34733 | B24: 792 | C24: =IF(OR(B24="",B23=""),"",LN(B24/B23)) | D24: =STDEV(C5:C24)*SQRT(252) | E24: 99.75 | F24: =IF(OR(E24="",E23=""),"",LN(E24/E23)) | G24: 8.4584 | H24: =IF(OR(G24="",G23=""),"",LN(G24/G23)) | J24: 10.98 | K24: 7.49
A25: 34736 | B25: 794.7 | C25: =IF(OR(B25="",B24=""),"",LN(B25/B24)) | D25: =STDEV(C6:C25)*SQRT(252) | E25: 99.3 | F25: =IF(OR(E25="",E24=""),"",LN(E25/E24)) | G25: 8.458 | H25: =IF(OR(G25="",G24=""),"",LN(G25/G24)) | J25: 11.22 | K25: 7.53
A26: 34737 | B26: 795.2 | C26: =IF(OR(B26="",B25=""),"",LN(B26/B25)) | D26: =STDEV(C7:C26)*SQRT(252) | E26: 99.42 | F26: =IF(OR(E26="",E25=""),"",LN(E26/E25)) | G26: 8.4575 | H26: =IF(OR(G26="",G25=""),"",LN(G26/G25)) | J26: 11.17 | K26: 7.52
A27: 34738 | B27: 793 | C27: =IF(OR(B27="",B26=""),"",LN(B27/B26)) | D27: =STDEV(C8:C27)*SQRT(252) | E27: 98.98 | F27: =IF(OR(E27="",E26=""),"",LN(E27/E26)) | G27: 8.457 | H27: =IF(OR(G27="",G26=""),"",LN(G27/G26)) | J27: 11.42 | K27: 7.53
A28: 34739 | B28: 793.4 | C28: =IF(OR(B28="",B27=""),"",LN(B28/B27)) | D28: =STDEV(C9:C28)*SQRT(252) | E28: 98.85 | F28: =IF(OR(E28="",E27=""),"",LN(E28/E27)) | G28: 8.4564 | H28: =IF(OR(G28="",G27=""),"",LN(G28/G27)) | J28: 11.63 | K28: 7.58
A29: 34740 | B29: 793.9 | C29: =IF(OR(B29="",B28=""),"",LN(B29/B28)) | D29: =STDEV(C10:C29)*SQRT(252) | E29: 98.86 | F29: =IF(OR(E29="",E28=""),"",LN(E29/E28)) | G29: 8.456 | H29: =IF(OR(G29="",G28=""),"",LN(G29/G28)) | J29: 11.28 | K29: 7.62
A30: 34743 | B30: 796.6 | C30: =IF(OR(B30="",B29=""),"",LN(B30/B29)) | D30: =STDEV(C11:C30)*SQRT(252) | E30: 98.66 | F30: =IF(OR(E30="",E29=""),"",LN(E30/E29)) | G30: 8.4555 | H30: =IF(OR(G30="",G29=""),"",LN(G30/G29)) | J30: 11.41 | K30: 7.61
A31: 34744 | B31: 796.3 | C31: =IF(OR(B31="",B30=""),"",LN(B31/B30)) | D31: =STDEV(C12:C31)*SQRT(252) | E31: 98.65 | F31: =IF(OR(E31="",E30=""),"",LN(E31/E30)) | G31: 8.4552 | H31: =IF(OR(G31="",G30=""),"",LN(G31/G30)) | J31: 11.43 | K31: 7.51
A32: 34745 | B32: 794.1 | C32: =IF(OR(B32="",B31=""),"",LN(B32/B31)) | D32: =STDEV(C13:C32)*SQRT(252) | E32: 98.52 | F32: =IF(OR(E32="",E31=""),"",LN(E32/E31)) | G32: 8.4551 | H32: =IF(OR(G32="",G31=""),"",LN(G32/G31)) | J32: 11.52 | K32: 7.45
A33: 34746 | B33: 794.4 | C33: =IF(OR(B33="",B32=""),"",LN(B33/B32)) | D33: =STDEV(C14:C33)*SQRT(252) | E33: 97.55 | F33: =IF(OR(E33="",E32=""),"",LN(E33/E32)) | G33: 8.4552 | H33: =IF(OR(G33="",G32=""),"",LN(G33/G32)) | J33: 11.61 | K33: 7.4
... A72: 34802 | B72: 772.6 | C72: =IF(OR(B72="",B71=""),"",LN(B72/B71)) | D72: =STDEV(C53:C72)*SQRT(252) | E72: 83.59 | F72: =IF(OR(E72="",E71=""),"",LN(E72/E71)) | G72: 8.4442 | H72: =IF(OR(G72="",G71=""),"",LN(G72/G71)) | J72: 11.48 | K72: 7.03
A73: 34803 | B73: 773.4 | C73: =IF(OR(B73="",B72=""),"",LN(B73/B72)) | D73: =STDEV(C54:C73)*SQRT(252) | E73: 83.35 | F73: =IF(OR(E73="",E72=""),"",LN(E73/E72)) | G73: 8.4441 | H73: =IF(OR(G73="",G72=""),"",LN(G73/G72))
A74: 34806 | B74: 773.2 | C74: =IF(OR(B74="",B73=""),"",LN(B74/B73)) | D74: =STDEV(C55:C74)*SQRT(252) | E74: 82.1 | F74: =IF(OR(E74="",E73=""),"",LN(E74/E73)) | G74: 8.4438 | H74: =IF(OR(G74="",G73=""),"",LN(G74/G73)) | J74: 12.33 | K74: 7.04
A75: 34807 | B75: 771.8 | C75: =IF(OR(B75="",B74=""),"",LN(B75/B74)) | D75: =STDEV(C56:C75)*SQRT(252) | E75: 81.4 | F75: =IF(OR(E75="",E74=""),"",LN(E75/E74)) | G75: 8.4436 | H75: =IF(OR(G75="",G74=""),"",LN(G75/G74)) | J75: 12.96 | K75: 7.04
A76: 34808 | B76: 770.7 | C76: =IF(OR(B76="",B75=""),"",LN(B76/B75)) | D76: =STDEV(C57:C76)*SQRT(252) | E76: 81.12 | F76: =IF(OR(E76="",E75=""),"",LN(E76/E75)) | G76: 8.4434 | H76: =IF(OR(G76="",G75=""),"",LN(G76/G75)) | J76: 13.09 | K76: 7.06
A77: 34809 | B77: 769.3 | C77: =IF(OR(B77="",B76=""),"",LN(B77/B76)) | D77: =STDEV(C58:C77)*SQRT(252) | E77: 82.95 | F77: =IF(OR(E77="",E76=""),"",LN(E77/E76)) | G77: 8.4432 | H77: =IF(OR(G77="",G76=""),"",LN(G77/G76)) | J77: 12.1 | K77: 7.02
A78: 34810 | B78: 768.7 | C78: =IF(OR(B78="",B77=""),"",LN(B78/B77)) | D78: =STDEV(C59:C78)*SQRT(252) | E78: 82.92 | F78: =IF(OR(E78="",E77=""),"",LN(E78/E77)) | G78: 8.443 | H78: =IF(OR(G78="",G77=""),"",LN(G78/G77)) | J78: 11.86 | K78: 7.01
A79: 34813 | B79: 767.4 | C79: =IF(OR(B79="",B78=""),"",LN(B79/B78)) | D79: =STDEV(C60:C79)*SQRT(252) | E79: 83.26 | F79: =IF(OR(E79="",E78=""),"",LN(E79/E78)) | G79: 8.4427 | H79: =IF(OR(G79="",G78=""),"",LN(G79/G78)) | J79: 11.92 | K79: 7.01
A80: 34814 | B80: 765.8 | C80: =IF(OR(B80="",B79=""),"",LN(B80/B79)) | D80: =STDEV(C61:C80)*SQRT(252) | E80: 81.95 | F80: =IF(OR(E80="",E79=""),"",LN(E80/E79)) | G80: 8.4405 | H80: =IF(OR(G80="",G79=""),"",LN(G80/G79)) | J80: 12.41 | K80: 7.01
A81: 34815 | B81: 764.9 | C81: =IF(OR(B81="",B80=""),"",LN(B81/B80)) | D81: =STDEV(C62:C81)*SQRT(252) | E81: 83.98 | F81: =IF(OR(E81="",E80=""),"",LN(E81/E80)) | G81: 8.4338 | H81: =IF(OR(G81="",G80=""),"",LN(G81/G80)) | J81: 12.28 | K81: 7.01
A82: 34816 | B82: 764.8 | C82: =IF(OR(B82="",B81=""),"",LN(B82/B81)) | D82: =STDEV(C63:C82)*SQRT(252) | E82: 83.58 | F82: =IF(OR(E82="",E81=""),"",LN(E82/E81)) | G82: 8.4302 | H82: =IF(OR(G82="",G81=""),"",LN(G82/G81)) | J82: 11.93 | K82: 7.04
A83: 34817 | B83: 763.9 | C83: =IF(OR(B83="",B82=""),"",LN(B83/B82)) | D83: =STDEV(C64:C83)*SQRT(252) | E83: 84.04 | F83: =IF(OR(E83="",E82=""),"",LN(E83/E82)) | G83: 8.4274 | H83: =IF(OR(G83="",G82=""),"",LN(G83/G82)) | J83: 11.75 | K83: 7.07
A84: 34820 | B84: 764.8 | C84: =IF(OR(B84="",B83=""),"",LN(B84/B83)) | D84: =STDEV(C65:C84)*SQRT(252) | E84: 83.53 | F84: =IF(OR(E84="",E83=""),"",LN(E84/E83)) | G84: 8.4274 | H84: =IF(OR(G84="",G83=""),"",LN(G84/G83)) | J84: 12.14 | K84: 7.09
A85: 34821 | B85: 764.8 | C85: =IF(OR(B85="",B84=""),"",LN(B85/B84)) | D85: =STDEV(C66:C85)*SQRT(252) | E85: 83.69 | F85: =IF(OR(E85="",E84=""),"",LN(E85/E84)) | G85: 8.4152 | H85: =IF(OR(G85="",G84=""),"",LN(G85/G84)) | J85: 11.88 | K85: 7.04
... A318: 35159 | B318: 780.1 | C318: =IF(OR(B318="",B317=""),"",LN(B318/B317)) | D318: =STDEV(C299:C318)*SQRT(252) | E318: 107.09 | F318: =IF(OR(E318="",E317=""),"",LN(E318/E317)) | G318: 8.3525 | H318: =IF(OR(G318="",G317=""),"",LN(G318/G317)) | J318: 16.18 | K318: 6.33
A319: 35160 | B319: 780.1 | C319: =IF(OR(B319="",B318=""),"",LN(B319/B318)) | D319: =STDEV(C300:C319)*SQRT(252) | E319: 107.67 | F319: =IF(OR(E319="",E318=""),"",LN(E319/E318)) | G319: 8.3511 | H319: =IF(OR(G319="",G318=""),"",LN(G319/G318)) | K319: 6.57
A320: 35163 | B320: 780.1 | C320: =IF(OR(B320="",B319=""),"",LN(B320/B319)) | D320: =STDEV(C301:C320)*SQRT(252) | E320: 107.42 | F320: =IF(OR(E320="",E319=""),"",LN(E320/E319)) | G320: 8.3512 | H320: =IF(OR(G320="",G319=""),"",LN(G320/G319)) | J320: 18.72 | K320: 6.63
A321: 35164 | B321: 780.8 | C321: =IF(OR(B321="",B320=""),"",LN(B321/B320)) | D321: =STDEV(C302:C321)*SQRT(252) | E321: 108.18 | F321: =IF(OR(E321="",E320=""),"",LN(E321/E320)) | G321: 8.3515 | H321: =IF(OR(G321="",G320=""),"",LN(G321/G320)) | J321: 17.32 | K321: 6.56
A322: 35165 | B322: 782.2 | C322: =IF(OR(B322="",B321=""),"",LN(B322/B321)) | D322: =STDEV(C303:C322)*SQRT(252) | E322: 108.56 | F322: =IF(OR(E322="",E321=""),"",LN(E322/E321)) | G322: 8.3518 | H322: =IF(OR(G322="",G321=""),"",LN(G322/G321)) | J322: 20.22 | K322: 6.63
A323: 35166 | B323: 782.2 | C323: =IF(OR(B323="",B322=""),"",LN(B323/B322)) | D323: =STDEV(C304:C323)*SQRT(252) | E323: 108.52 | F323: =IF(OR(E323="",E322=""),"",LN(E323/E322)) | G323: 8.3524 | H323: =IF(OR(G323="",G322=""),"",LN(G323/G322)) | J323: 19.65 | K323: 6.68
A324: 35167 | B324: 782.8 | C324: =IF(OR(B324="",B323=""),"",LN(B324/B323)) | D324: =STDEV(C305:C324)*SQRT(252) | E324: 108.67 | F324: =IF(OR(E324="",E323=""),"",LN(E324/E323)) | G324: 8.3522 | H324: =IF(OR(G324="",G323=""),"",LN(G324/G323)) | J324: 17.38 | K324: 6.52
A325: 35170 | B325: 782.8 | C325: =IF(OR(B325="",B324=""),"",LN(B325/B324)) | D325: =STDEV(C306:C325)*SQRT(252) | E325: 108.36 | F325: =IF(OR(E325="",E324=""),"",LN(E325/E324)) | G325: 8.3521 | H325: =IF(OR(G325="",G324=""),"",LN(G325/G324)) | J325: 16.83 | K325: 6.47
A326: 35171 | B326: 781.9 | C326: =IF(OR(B326="",B325=""),"",LN(B326/B325)) | D326: =STDEV(C307:C326)*SQRT(252) | E326: 108.28 | F326: =IF(OR(E326="",E325=""),"",LN(E326/E325)) | G326: 8.3517 | H326: =IF(OR(G326="",G325=""),"",LN(G326/G325)) | J326: 16.45 | K326: 6.48
A327: 35172 | B327: 781.7 | C327: =IF(OR(B327="",B326=""),"",LN(B327/B326)) | D327: =STDEV(C308:C327)*SQRT(252) | E327: 108.27 | F327: =IF(OR(E327="",E326=""),"",LN(E327/E326)) | G327: 8.3512 | H327: =IF(OR(G327="",G326=""),"",LN(G327/G326)) | J327: 17.07 | K327: 6.52
A328: 35173 | B328: 779.9 | C328: =IF(OR(B328="",B327=""),"",LN(B328/B327)) | D328: =STDEV(C309:C328)*SQRT(252) | E328: 107.1 | F328: =IF(OR(E328="",E327=""),"",LN(E328/E327)) | G328: 8.3509 | H328: =IF(OR(G328="",G327=""),"",LN(G328/G327)) | J328: 16.41 | K328: 6.58
A329: 35174 | B329: 779.1 | C329: =IF(OR(B329="",B328=""),"",LN(B329/B328)) | D329: =STDEV(C310:C329)*SQRT(252) | E329: 107.1 | F329: =IF(OR(E329="",E328=""),"",LN(E329/E328)) | G329: 8.3506 | H329: =IF(OR(G329="",G328=""),"",LN(G329/G328)) | J329: 15.12 | K329: 6.53
A330: 35177 | B330: 778.9 | C330: =IF(OR(B330="",B329=""),"",LN(B330/B329)) | D330: =STDEV(C311:C330)*SQRT(252) | E330: 106.7 | F330: =IF(OR(E330="",E329=""),"",LN(E330/E329)) | G330: 8.35 | H330: =IF(OR(G330="",G329=""),"",LN(G330/G329)) | J330: 15.38 | K330: 6.48
A331: 35178 | B331: 779.2 | C331: =IF(OR(B331="",B330=""),"",LN(B331/B330)) | D331: =STDEV(C312:C331)*SQRT(252) | E331: 106.59 | F331: =IF(OR(E331="",E330=""),"",LN(E331/E330)) | G331: 8.3502 | H331: =IF(OR(G331="",G330=""),"",LN(G331/G330)) | J331: 15.01 | K331: 6.52
... A524: 35460 | B524: 867 | C524: =IF(OR(B524="",B523=""),"",LN(B524/B523)) | D524: =STDEV(C505:C524)*SQRT(252) | E524: 121.55 | F524: =IF(OR(E524="",E523=""),"",LN(E524/E523)) | G524: 8.3238 | H524: =IF(OR(G524="",G523=""),"",LN(G524/G523)) | J524: 19.47 | K524: 6.61
A525: 35461 | B525: 867 | C525: =IF(OR(B525="",B524=""),"",LN(B525/B524)) | D525: =STDEV(C506:C525)*SQRT(252) | E525: 121.25 | F525: =IF(OR(E525="",E524=""),"",LN(E525/E524)) | G525: 8.3234 | H525: =IF(OR(G525="",G524=""),"",LN(G525/G524)) | K525: 6.53
A526: 35464 | B526: 869 | C526: =IF(OR(B526="",B525=""),"",LN(B526/B525)) | D526: =STDEV(C507:C526)*SQRT(252) | E526: 121.68 | F526: =IF(OR(E526="",E525=""),"",LN(E526/E525)) | G526: 8.3231 | H526: =IF(OR(G526="",G525=""),"",LN(G526/G525)) | J526: 19.58 | K526: 6.47
A527: 35465 | B527: 871 | C527: =IF(OR(B527="",B526=""),"",LN(B527/B526)) | D527: =STDEV(C508:C527)*SQRT(252) | E527: 122.34 | F527: =IF(OR(E527="",E526=""),"",LN(E527/E526)) | G527: 8.3227 | H527: =IF(OR(G527="",G526=""),"",LN(G527/G526)) | J527: 19.43 | K527: 6.45
A528: 35466 | B528: 872 | C528: =IF(OR(B528="",B527=""),"",LN(B528/B527)) | D528: =STDEV(C509:C528)*SQRT(252) | E528: 123.59 | F528: =IF(OR(E528="",E527=""),"",LN(E528/E527)) | G528: 8.3225 | H528: =IF(OR(G528="",G527=""),"",LN(G528/G527)) | J528: 21.06 | K528: 6.47
A529: 35467 | B529: 868 | C529: =IF(OR(B529="",B528=""),"",LN(B529/B528)) | D529: =STDEV(C510:C529)*SQRT(252) | E529: 123.82 | F529: =IF(OR(E529="",E528=""),"",LN(E529/E528)) | G529: 8.3216 | H529: =IF(OR(G529="",G528=""),"",LN(G529/G528)) | J529: 20.16 | K529: 6.49
A530: 35468 | B530: 872 | C530: =IF(OR(B530="",B529=""),"",LN(B530/B529)) | D530: =STDEV(C511:C530)*SQRT(252) | E530: 124.54 | F530: =IF(OR(E530="",E529=""),"",LN(E530/E529)) | G530: 8.3216 | H530: =IF(OR(G530="",G529=""),"",LN(G530/G529)) | J530: 18.9 | K530: 6.43
A531: 35471 | B531: 871.5 | C531: =IF(OR(B531="",B530=""),"",LN(B531/B530)) | D531: =STDEV(C512:C531)*SQRT(252) | E531: 122.74 | F531: =IF(OR(E531="",E530=""),"",LN(E531/E530)) | G531: 8.3216 | H531: =IF(OR(G531="",G530=""),"",LN(G531/G530)) | J531: 20.65 | K531: 6.43
A532: 35472 | B532: 871.5 | C532: =IF(OR(B532="",B531=""),"",LN(B532/B531)) | D532: =STDEV(C513:C532)*SQRT(252) | E532: 123.17 | F532: =IF(OR(E532="",E531=""),"",LN(E532/E531)) | G532: 8.3216 | H532: =IF(OR(G532="",G531=""),"",LN(G532/G531)) | J532: 19.97 | K532: 6.43
A533: 35473 | B533: 871.5 | C533: =IF(OR(B533="",B532=""),"",LN(B533/B532)) | D533: =STDEV(C514:C533)*SQRT(252) | E533: 124.02 | F533: =IF(OR(E533="",E532=""),"",LN(E533/E532)) | G533: 8.32 | H533: =IF(OR(G533="",G532=""),"",LN(G533/G532)) | J533: 19.48 | K533: 6.39
A534: 35474 | B534: 877.5 | C534: =IF(OR(B534="",B533=""),"",LN(B534/B533)) | D534: =STDEV(C515:C534)*SQRT(252) | E534: 124.35 | F534: =IF(OR(E534="",E533=""),"",LN(E534/E533)) | G534: 8.3222 | H534: =IF(OR(G534="",G533=""),"",LN(G534/G533)) | J534: 19.23 | K534: 6.32
A535: 35475 | B535: 877 | C535: =IF(OR(B535="",B534=""),"",LN(B535/B534)) | D535: =STDEV(C516:C535)*SQRT(252) | E535: 124.06 | F535: =IF(OR(E535="",E534=""),"",LN(E535/E534)) | G535: 8.3225 | H535: =IF(OR(G535="",G534=""),"",LN(G535/G534)) | J535: 19.18 | K535: 6.28
A536: 35479 | B536: 873 | C536: =IF(OR(B536="",B535=""),"",LN(B536/B535)) | D536: =STDEV(C517:C536)*SQRT(252) | E536: 123.92 | F536: =IF(OR(E536="",E535=""),"",LN(E536/E535)) | G536: 8.3221 | H536: =IF(OR(G536="",G535=""),"",LN(G536/G535)) | J536: 19.7 | K536: 6.28
A537: 35480 | B537: 862.5 | C537: =IF(OR(B537="",B536=""),"",LN(B537/B536)) | D537: =STDEV(C518:C537)*SQRT(252) | E537: 124.3 | F537: =IF(OR(E537="",E536=""),"",LN(E537/E536)) | G537: 8.3238 | H537: =IF(OR(G537="",G536=""),"",LN(G537/G536)) | J537: 20.61 | K537: 6.3
... A563: 35516 | B563: 896 | C563: =IF(OR(B563="",B562=""),"",LN(B563/B562)) | D563: =STDEV(C544:C563)*SQRT(252) | E563: 123.65 | F563: =IF(OR(E563="",E562=""),"",LN(E563/E562)) | G563: 8.3264 | H563: =IF(OR(G563="",G562=""),"",LN(G563/G562)) | J563: 20.5 | K563: 6.9
A564: 35517 | B564: 897.5 | C564: =IF(OR(B564="",B563=""),"",LN(B564/B563)) | D564: =STDEV(C545:C564)*SQRT(252) | E564: 123.9 | F564: =IF(OR(E564="",E563=""),"",LN(E564/E563)) | G564: 8.3264 | H564: =IF(OR(G564="",G563=""),"",LN(G564/G563))
A565: 35520 | B565: 898 | C565: =IF(OR(B565="",B564=""),"",LN(B565/B564)) | D565: =STDEV(C546:C565)*SQRT(252) | E565: 123.72 | F565: =IF(OR(E565="",E564=""),"",LN(E565/E564)) | G565: 8.3255 | H565: =IF(OR(G565="",G564=""),"",LN(G565/G564)) | J565: 22.14 | K565: 6.92
A566: 35521 | B566: 898 | C566: =IF(OR(B566="",B565=""),"",LN(B566/B565)) | D566: =STDEV(C547:C566)*SQRT(252) | E566: 122.7 | F566: =IF(OR(E566="",E565=""),"",LN(E566/E565)) | G566: 8.3253 | H566: =IF(OR(G566="",G565=""),"",LN(G566/G565)) | J566: 20.84 | K566: 6.9
A567: 35522 | B567: 897 | C567: =IF(OR(B567="",B566=""),"",LN(B567/B566)) | D567: =STDEV(C548:C567)*SQRT(252) | E567: 122.72 | F567: =IF(OR(E567="",E566=""),"",LN(E567/E566)) | G567: 8.3263 | H567: =IF(OR(G567="",G566=""),"",LN(G567/G566)) | J567: 21.3 | K567: 6.88
A568: 35523 | B568: 897 | C568: =IF(OR(B568="",B567=""),"",LN(B568/B567)) | D568: =STDEV(C549:C568)*SQRT(252) | E568: 122.8 | F568: =IF(OR(E568="",E567=""),"",LN(E568/E567)) | G568: 8.3269 | H568: =IF(OR(G568="",G567=""),"",LN(G568/G567)) | J568: 21.19 | K568: 6.86
A569: 35524 | B569: 895 | C569: =IF(OR(B569="",B568=""),"",LN(B569/B568)) | D569: =STDEV(C550:C569)*SQRT(252) | E569: 124.27 | F569: =IF(OR(E569="",E568=""),"",LN(E569/E568)) | G569: 8.3268 | H569: =IF(OR(G569="",G568=""),"",LN(G569/G568)) | J569: 19.23 | K569: 6.92
A570: 35527 | B570: 896 | C570: =IF(OR(B570="",B569=""),"",LN(B570/B569)) | D570: =STDEV(C551:C570)*SQRT(252) | E570: 125.67 | F570: =IF(OR(E570="",E569=""),"",LN(E570/E569)) | G570: 8.3266 | H570: =IF(OR(G570="",G569=""),"",LN(G570/G569)) | J570: 18.51 | K570: 6.87
A571: 35528 | B571: 896 | C571: =IF(OR(B571="",B570=""),"",LN(B571/B570)) | D571: =STDEV(C552:C571)*SQRT(252) | E571: 126.08 | F571: =IF(OR(E571="",E570=""),"",LN(E571/E570)) | G571: 8.3266 | H571: =IF(OR(G571="",G570=""),"",LN(G571/G570)) | J571: 18.44 | K571: 6.91
A572: 35529 | B572: 896 | C572: =IF(OR(B572="",B571=""),"",LN(B572/B571)) | D572: =STDEV(C553:C572)*SQRT(252) | E572: 126.86 | F572: =IF(OR(E572="",E571=""),"",LN(E572/E571)) | G572: 8.3265 | H572: =IF(OR(G572="",G571=""),"",LN(G572/G571)) | J572: 18.56 | K572: 6.91
A573: 35530 | B573: 895 | C573: =IF(OR(B573="",B572=""),"",LN(B573/B572)) | D573: =STDEV(C554:C573)*SQRT(252) | E573: 125.95 | F573: =IF(OR(E573="",E572=""),"",LN(E573/E572)) | G573: 8.3265 | H573: =IF(OR(G573="",G572=""),"",LN(G573/G572)) | J573: 19.01 | K573: 6.91
A574: 35531 | B574: 895 | C574: =IF(OR(B574="",B573=""),"",LN(B574/B573)) | D574: =STDEV(C555:C574)*SQRT(252) | E574: 126.04 | F574: =IF(OR(E574="",E573=""),"",LN(E574/E573)) | G574: 8.3269 | H574: =IF(OR(G574="",G573=""),"",LN(G574/G573)) | J574: 19.76 | K574: 6.98
A575: 35534 | B575: 896.5 | C575: =IF(OR(B575="",B574=""),"",LN(B575/B574)) | D575: =STDEV(C556:C575)*SQRT(252) | E575: 126.48 | F575: =IF(OR(E575="",E574=""),"",LN(E575/E574)) | G575: 8.3265 | H575: =IF(OR(G575="",G574=""),"",LN(G575/G574)) | J575: 19.09 | K575: 6.98
A576: 35535 | B576: 897 | C576: =IF(OR(B576="",B575=""),"",LN(B576/B575)) | D576: =STDEV(C557:C576)*SQRT(252) | E576: 126.35 | F576: =IF(OR(E576="",E575=""),"",LN(E576/E575)) | G576: 8.3261 | H576: =IF(OR(G576="",G575=""),"",LN(G576/G575)) | J576: 18.25 | K576: 6.88
... A676: 35678 | B676: 909 | C676: =IF(OR(B676="",B675=""),"",LN(B676/B675)) | D676: =STDEV(C657:C676)*SQRT(252) | E676: 121.09 | F676: =IF(OR(E676="",E675=""),"",LN(E676/E675)) | G676: 8.3184 | H676: =IF(OR(G676="",G675=""),"",LN(G676/G675)) | J676: 24.31 | K676: 6.37
A677: 35681 | B677: 910 | C677: =IF(OR(B677="",B676=""),"",LN(B677/B676)) | D677: =STDEV(C658:C677)*SQRT(252) | E677: 121.02 | F677: =IF(OR(E677="",E676=""),"",LN(E677/E676)) | H677: =IF(OR(G677="",G676=""),"",LN(G677/G676)) | J677: 24.4 | K677: 6.33
A678: 35682 | B678: 911 | C678: =IF(OR(B678="",B677=""),"",LN(B678/B677)) | D678: =STDEV(C659:C678)*SQRT(252) | E678: 119.05 | F678: =IF(OR(E678="",E677=""),"",LN(E678/E677)) | G678: 8.3181 | H678: =IF(OR(G678="",G677=""),"",LN(G678/G677)) | J678: 23.89 | K678: 6.34
A679: 35683 | B679: 911 | C679: =IF(OR(B679="",B678=""),"",LN(B679/B678)) | D679: =STDEV(C660:C679)*SQRT(252) | E679: 119.26 | F679: =IF(OR(E679="",E678=""),"",LN(E679/E678)) | G679: 8.3187 | H679: =IF(OR(G679="",G678=""),"",LN(G679/G678)) | J679: 24.64 | K679: 6.37
A680: 35684 | B680: 911 | C680: =IF(OR(B680="",B679=""),"",LN(B680/B679)) | D680: =STDEV(C661:C680)*SQRT(252) | E680: 119.58 | F680: =IF(OR(E680="",E679=""),"",LN(E680/E679)) | G680: 8.3189 | H680: =IF(OR(G680="",G679=""),"",LN(G680/G679)) | J680: 25.99 | K680: 6.39
A681: 35685 | B681: 911 | C681: =IF(OR(B681="",B680=""),"",LN(B681/B680)) | D681: =STDEV(C662:C681)*SQRT(252) | E681: 120.93 | F681: =IF(OR(E681="",E680=""),"",LN(E681/E680)) | G681: 8.3181 | H681: =IF(OR(G681="",G680=""),"",LN(G681/G680)) | J681: 25.17 | K681: 6.29
A682: 35688 | B682: 911 | C682: =IF(OR(B682="",B681=""),"",LN(B682/B681)) | D682: =STDEV(C663:C682)*SQRT(252) | E682: 120.4 | F682: =IF(OR(E682="",E681=""),"",LN(E682/E681)) | G682: 8.3181 | H682: =IF(OR(G682="",G681=""),"",LN(G682/G681)) | J682: 25.74 | K682: 6.28
A683: 35689 | B683: 911 | C683: =IF(OR(B683="",B682=""),"",LN(B683/B682)) | D683: =STDEV(C664:C683)*SQRT(252) | E683: 121.1 | F683: =IF(OR(E683="",E682=""),"",LN(E683/E682)) | G683: 8.3171 | H683: =IF(OR(G683="",G682=""),"",LN(G683/G682)) | J683: 23.77 | K683: 6.11
A684: 35690 | B684: 911 | C684: =IF(OR(B684="",B683=""),"",LN(B684/B683)) | D684: =STDEV(C665:C684)*SQRT(252) | E684: 120.99 | F684: =IF(OR(E684="",E683=""),"",LN(E684/E683)) | G684: 8.3175 | H684: =IF(OR(G684="",G683=""),"",LN(G684/G683)) | J684: 24.1 | K684: 6.1
A685: 35691 | B685: 912 | C685: =IF(OR(B685="",B684=""),"",LN(B685/B684)) | D685: =STDEV(C666:C685)*SQRT(252) | E685: 121.98 | F685: =IF(OR(E685="",E684=""),"",LN(E685/E684)) | G685: 8.3173 | H685: =IF(OR(G685="",G684=""),"",LN(G685/G684)) | J685: 23.48 | K685: 6.11
A686: 35692 | B686: 916 | C686: =IF(OR(B686="",B685=""),"",LN(B686/B685)) | D686: =STDEV(C667:C686)*SQRT(252) | E686: 121.93 | F686: =IF(OR(E686="",E685=""),"",LN(E686/E685)) | G686: 8.3164 | H686: =IF(OR(G686="",G685=""),"",LN(G686/G685)) | J686: 22.74 | K686: 6.09
A687: 35695 | B687: 916 | C687: =IF(OR(B687="",B686=""),"",LN(B687/B686)) | D687: =STDEV(C668:C687)*SQRT(252) | E687: 122.25 | F687: =IF(OR(E687="",E686=""),"",LN(E687/E686)) | G687: 8.3159 | H687: =IF(OR(G687="",G686=""),"",LN(G687/G686)) | J687: 22.08 | K687: 6.06
A688: 35696 | B688: 916 | C688: =IF(OR(B688="",B687=""),"",LN(B688/B687)) | D688: =STDEV(C669:C688)*SQRT(252) | E688: 121.53 | F688: =IF(OR(E688="",E687=""),"",LN(E688/E687)) | G688: 8.3154 | H688: =IF(OR(G688="",G687=""),"",LN(G688/G687)) | J688: 22 | K688: 6.1
A689: 35697 | B689: 916 | C689: =IF(OR(B689="",B688=""),"",LN(B689/B688)) | D689: =STDEV(C670:C689)*SQRT(252) | E689: 120.4 | F689: =IF(OR(E689="",E688=""),"",LN(E689/E688)) | G689: 8.3151 | H689: =IF(OR(G689="",G688=""),"",LN(G689/G688)) | J689: 22.64 | K689: 6.04
... A730: 35759 | B730: 1122 | C730: =IF(OR(B730="",B729=""),"",LN(B730/B729)) | D730: =STDEV(C711:C730)*SQRT(252) | E730: 127.45 | F730: =IF(OR(E730="",E729=""),"",LN(E730/E729)) | G730: 8.31 | H730: =IF(OR(G730="",G729=""),"",LN(G730/G729)) | J730: 28.95 | K730: 5.85
A731: 35760 | B731: 1110 | C731: =IF(OR(B731="",B730=""),"",LN(B731/B730)) | D731: =STDEV(C712:C731)*SQRT(252) | E731: 127.51 | F731: =IF(OR(E731="",E730=""),"",LN(E731/E730)) | G731: 8.3101 | H731: =IF(OR(G731="",G730=""),"",LN(G731/G730)) | K731: 5.86
A732: 35762 | B732: 1169.5 | C732: =IF(OR(B732="",B731=""),"",LN(B732/B731)) | D732: =STDEV(C713:C732)*SQRT(252) | E732: 127.74 | F732: =IF(OR(E732="",E731=""),"",LN(E732/E731)) | G732: 8.3096 | H732: =IF(OR(G732="",G731=""),"",LN(G732/G731)) | J732: 27.43 | K732: 5.86
...

Sheet Rates_Monthly
A1: Month | B1: KRW 3M % | C1: USD 3M % | D1: Gap (pts) | E1: USD/KRW avg | F1: Implied 3M pts (won) | G1: Hedge carry (ann.)
A2: 34700 | B2: 15.72 | C2: 6.24 | D2: =B2-C2 | E2: =IFERROR(AVERAGEIFS(Daily!$B:$B,Daily!$A:$A,">="&A2,Daily!$A:$A,"<"&EDATE(A2,1)),"") | F2: =IF(E2="","",E2*((1+B2/100*91/365)/(1+C2/100*91/360)-1)) | G2: =IF(E2="","",(F2/E2)*365/91)
A3: 34731 | B3: 16.65 | C3: 6.16 | D3: =B3-C3 | E3: =IFERROR(AVERAGEIFS(Daily!$B:$B,Daily!$A:$A,">="&A3,Daily!$A:$A,"<"&EDATE(A3,1)),"") | F3: =IF(E3="","",E3*((1+B3/100*91/365)/(1+C3/100*91/360)-1)) | G3: =IF(E3="","",(F3/E3)*365/91)
A4: 34759 | B4: 15.33 | C4: 6.15 | D4: =B4-C4 | E4: =IFERROR(AVERAGEIFS(Daily!$B:$B,Daily!$A:$A,">="&A4,Daily!$A:$A,"<"&EDATE(A4,1)),"") | F4: =IF(E4="","",E4*((1+B4/100*91/365)/(1+C4/100*91/360)-1)) | G4: =IF(E4="","",(F4/E4)*365/91)
A5: 34790 | B5: 14.56 | C5: 6.11 | D5: =B5-C5 | E5: =IFERROR(AVERAGEIFS(Daily!$B:$B,Daily!$A:$A,">="&A5,Daily!$A:$A,"<"&EDATE(A5,1)),"") | F5: =IF(E5="","",E5*((1+B5/100*91/365)/(1+C5/100*91/360)-1)) | G5: =IF(E5="","",(F5/E5)*365/91)
A6: 34820 | B6: 14.87 | C6: 6.02 | D6: =B6-C6 | E6: =IFERROR(AVERAGEIFS(Daily!$B:$B,Daily!$A:$A,">="&A6,Daily!$A:$A,"<"&EDATE(A6,1)),"") | F6: =IF(E6="","",E6*((1+B6/100*91/365)/(1+C6/100*91/360)-1)) | G6: =IF(E6="","",(F6/E6)*365/91)
A7: 34851 | B7: 14.73 | C7: 5.9 | D7: =B7-C7 | E7: =IFERROR(AVERAGEIFS(Daily!$B:$B,Daily!$A:$A,">="&A7,Daily!$A:$A,"<"&EDATE(A7,1)),"") | F7: =IF(E7="","",E7*((1+B7/100*91/365)/(1+C7/100*91/360)-1)) | G7: =IF(E7="","",(F7/E7)*365/91)
A8: 34881 | B8: 14.24 | C8: 5.77 | D8: =B8-C8 | E8: =IFERROR(AVERAGEIFS(Daily!$B:$B,Daily!$A:$A,">="&A8,Daily!$A:$A,"<"&EDATE(A8,1)),"") | F8: =IF(E8="","",E8*((1+B8/100*91/365)/(1+C8/100*91/360)-1)) | G8: =IF(E8="","",(F8/E8)*365/91)
A9: 34912 | B9: 13.45 | C9: 5.77 | D9: =B9-C9 | E9: =IFERROR(AVERAGEIFS(Daily!$B:$B,Daily!$A:$A,">="&A9,Daily!$A:$A,"<"&EDATE(A9,1)),"") | F9: =IF(E9="","",E9*((1+B9/100*91/365)/(1+C9/100*91/360)-1)) | G9: =IF(E9="","",(F9/E9)*365/91)
A10: 34943 | B10: 13.1 | C10: 5.73 | D10: =B10-C10 | E10: =IFERROR(AVERAGEIFS(Daily!$B:$B,Daily!$A:$A,">="&A10,Daily!$A:$A,"<"&EDATE(A10,1)),"") | F10: =IF(E10="","",E10*((1+B10/100*91/365)/(1+C10/100*91/360)-1)) | G10: =IF(E10="","",(F10/E10)*365/91)
A11: 34973 | B11: 12.32 | C11: 5.79 | D11: =B11-C11 | E11: =IFERROR(AVERAGEIFS(Daily!$B:$B,Daily!$A:$A,">="&A11,Daily!$A:$A,"<"&EDATE(A11,1)),"") | F11: =IF(E11="","",E11*((1+B11/100*91/365)/(1+C11/100*91/360)-1)) | G11: =IF(E11="","",(F11/E11)*365/91)
A12: 35004 | B12: 11.95 | C12: 5.74 | D12: =B12-C12 | E12: =IFERROR(AVERAGEIFS(Daily!$B:$B,Daily!$A:$A,">="&A12,Daily!$A:$A,"<"&EDATE(A12,1)),"") | F12: =IF(E12="","",E12*((1+B12/100*91/365)/(1+C12/100*91/360)-1)) | G12: =IF(E12="","",(F12/E12)*365/91)
A13: 35034 | B13: 11.73 | C13: 5.62 | D13: =B13-C13 | E13: =IFERROR(AVERAGEIFS(Daily!$B:$B,Daily!$A:$A,">="&A13,Daily!$A:$A,"<"&EDATE(A13,1)),"") | F13: =IF(E13="","",E13*((1+B13/100*91/365)/(1+C13/100*91/360)-1)) | G13: =IF(E13="","",(F13/E13)*365/91)
... A380: 46235 | B380: 2.97 | C380: 3.82 | D380: =B380-C380 | E380: =IFERROR(AVERAGEIFS(Daily!$B:$B,Daily!$A:$A,">="&A380,Daily!$A:$A,"<"&EDATE(A380,1)),"") | F380: =IF(E380="","",E380*((1+B380/100*91/365)/(1+C380/100*91/360)-1)) | G380: =IF(E380="","",(F380/E380)*365/91)

Sheet Macro_Annual
A1: Year | B1: KR GDP % | C1: US GDP % | D1: Growth gap | E1: KR CPI % | F1: US CPI % | G1: Inflation gap | H1: KR current acct % GDP | I1: USD/KRW Dec avg | J1: USD/KRW chg (log)
A2: 1996 | B2: 7.9904298 | C2: 3.7727727 | D2: =IF(OR(B2="",C2=""),"",B2-C2) | E2: 4.9245435 | F2: 2.9312042 | G2: =IF(OR(E2="",F2=""),"",E2-F2) | H2: -3.875352 | I2: =IFERROR(AVERAGEIFS(Daily!$B:$B,Daily!$A:$A,">="&DATE(VALUE(A2),12,1),Daily!$A:$A,"<"&DATE(VALUE(A2)+1,1,1)),"")
A3: 1997 | B3: 6.2821927 | C3: 4.4471279 | D3: =IF(OR(B3="",C3=""),"",B3-C3) | E3: 4.4389318 | F3: 2.3376899 | G3: =IF(OR(E3="",F3=""),"",E3-F3) | H3: -1.8349378 | I3: =IFERROR(AVERAGEIFS(Daily!$B:$B,Daily!$A:$A,">="&DATE(VALUE(A3),12,1),Daily!$A:$A,"<"&DATE(VALUE(A3)+1,1,1)),"") | J3: =IF(OR(I3="",I2="",ROW()=2),"",LN(I3/I2))
A4: 1998 | B4: -4.9389297 | C4: 4.4831334 | D4: =IF(OR(B4="",C4=""),"",B4-C4) | E4: 7.5135801 | F4: 1.5522791 | G4: =IF(OR(E4="",F4=""),"",E4-F4) | H4: 10.096421 | I4: =IFERROR(AVERAGEIFS(Daily!$B:$B,Daily!$A:$A,">="&DATE(VALUE(A4),12,1),Daily!$A:$A,"<"&DATE(VALUE(A4)+1,1,1)),"") | J4: =IF(OR(I4="",I3="",ROW()=2),"",LN(I4/I3))
A5: 1999 | B5: 11.617263 | C5: 4.788425 | D5: =IF(OR(B5="",C5=""),"",B5-C5) | E5: 0.81295725 | F5: 2.1880272 | G5: =IF(OR(E5="",F5=""),"",E5-F5) | H5: 4.2243016 | I5: =IFERROR(AVERAGEIFS(Daily!$B:$B,Daily!$A:$A,">="&DATE(VALUE(A5),12,1),Daily!$A:$A,"<"&DATE(VALUE(A5)+1,1,1)),"") | J5: =IF(OR(I5="",I4="",ROW()=2),"",LN(I5/I4))
A6: 2000 | B6: 9.2018584 | C6: 4.0775858 | D6: =IF(OR(B6="",C6=""),"",B6-C6) | E6: 2.2591658 | F6: 3.3768573 | G6: =IF(OR(E6="",F6=""),"",E6-F6) | H6: 1.7039362 | I6: =IFERROR(AVERAGEIFS(Daily!$B:$B,Daily!$A:$A,">="&DATE(VALUE(A6),12,1),Daily!$A:$A,"<"&DATE(VALUE(A6)+1,1,1)),"") | J6: =IF(OR(I6="",I5="",ROW()=2),"",LN(I6/I5))
A7: 2001 | B7: 4.7259356 | C7: 0.95553834 | D7: =IF(OR(B7="",C7=""),"",B7-C7) | E7: 4.0665759 | F7: 2.8261711 | G7: =IF(OR(E7="",F7=""),"",E7-F7) | H7: 0.38148948 | I7: =IFERROR(AVERAGEIFS(Daily!$B:$B,Daily!$A:$A,">="&DATE(VALUE(A7),12,1),Daily!$A:$A,"<"&DATE(VALUE(A7)+1,1,1)),"") | J7: =IF(OR(I7="",I6="",ROW()=2),"",LN(I7/I6))
A8: 2002 | B8: 7.743999 | C8: 1.7004473 | D8: =IF(OR(B8="",C8=""),"",B8-C8) | E8: 2.7622621 | F8: 1.5860316 | G8: =IF(OR(E8="",F8=""),"",E8-F8) | H8: 0.62554 | I8: =IFERROR(AVERAGEIFS(Daily!$B:$B,Daily!$A:$A,">="&DATE(VALUE(A8),12,1),Daily!$A:$A,"<"&DATE(VALUE(A8)+1,1,1)),"") | J8: =IF(OR(I8="",I7="",ROW()=2),"",LN(I8/I7))
A9: 2003 | B9: 3.0747266 | C9: 2.795606 | D9: =IF(OR(B9="",C9=""),"",B9-C9) | E9: 3.5148745 | F9: 2.270095 | G9: =IF(OR(E9="",F9=""),"",E9-F9) | H9: 1.5522366 | I9: =IFERROR(AVERAGEIFS(Daily!$B:$B,Daily!$A:$A,">="&DATE(VALUE(A9),12,1),Daily!$A:$A,"<"&DATE(VALUE(A9)+1,1,1)),"") | J9: =IF(OR(I9="",I8="",ROW()=2),"",LN(I9/I8))
A10: 2004 | B10: 5.1836369 | C10: 3.8477717 | D10: =IF(OR(B10="",C10=""),"",B10-C10) | E10: 3.590663 | F10: 2.6772367 | G10: =IF(OR(E10="",F10=""),"",E10-F10) | H10: 3.5578331 | I10: =IFERROR(AVERAGEIFS(Daily!$B:$B,Daily!$A:$A,">="&DATE(VALUE(A10),12,1),Daily!$A:$A,"<"&DATE(VALUE(A10)+1,1,1)),"") | J10: =IF(OR(I10="",I9="",ROW()=2),"",LN(I10/I9))
A11: 2005 | B11: 4.3582367 | C11: 3.4835499 | D11: =IF(OR(B11="",C11=""),"",B11-C11) | E11: 2.7537916 | F11: 3.3927468 | G11: =IF(OR(E11="",F11=""),"",E11-F11) | H11: 1.2563644 | I11: =IFERROR(AVERAGEIFS(Daily!$B:$B,Daily!$A:$A,">="&DATE(VALUE(A11),12,1),Daily!$A:$A,"<"&DATE(VALUE(A11)+1,1,1)),"") | J11: =IF(OR(I11="",I10="",ROW()=2),"",LN(I11/I10))
A12: 2006 | B12: 5.2450055 | C12: 2.7845396 | D12: =IF(OR(B12="",C12=""),"",B12-C12) | E12: 2.2423403 | F12: 3.2259441 | G12: =IF(OR(E12="",F12=""),"",E12-F12) | H12: 0.19127527 | I12: =IFERROR(AVERAGEIFS(Daily!$B:$B,Daily!$A:$A,">="&DATE(VALUE(A12),12,1),Daily!$A:$A,"<"&DATE(VALUE(A12)+1,1,1)),"") | J12: =IF(OR(I12="",I11="",ROW()=2),"",LN(I12/I11))
A13: 2007 | B13: 5.8419634 | C13: 2.0038583 | D13: =IF(OR(B13="",C13=""),"",B13-C13) | E13: 2.5345738 | F13: 2.8526725 | G13: =IF(OR(E13="",F13=""),"",E13-F13) | H13: 0.8577605 | I13: =IFERROR(AVERAGEIFS(Daily!$B:$B,Daily!$A:$A,">="&DATE(VALUE(A13),12,1),Daily!$A:$A,"<"&DATE(VALUE(A13)+1,1,1)),"") | J13: =IF(OR(I13="",I12="",ROW()=2),"",LN(I13/I12))
A14: 2008 | B14: 3.0044045 | C14: 0.11358725 | D14: =IF(OR(B14="",C14=""),"",B14-C14) | E14: 4.6738966 | F14: 3.8391003 | G14: =IF(OR(E14="",F14=""),"",E14-F14) | H14: 0.1605928 | I14: =IFERROR(AVERAGEIFS(Daily!$B:$B,Daily!$A:$A,">="&DATE(VALUE(A14),12,1),Daily!$A:$A,"<"&DATE(VALUE(A14)+1,1,1)),"") | J14: =IF(OR(I14="",I13="",ROW()=2),"",LN(I14/I13))
... A30: 2024 | B30: 2.003611 | C30: 2.7931872 | D30: =IF(OR(B30="",C30=""),"",B30-C30) | E30: 2.3217433 | F30: 2.9495252 | G30: =IF(OR(E30="",F30=""),"",E30-F30) | H30: 5.3308163 | I30: =IFERROR(AVERAGEIFS(Daily!$B:$B,Daily!$A:$A,">="&DATE(VALUE(A30),12,1),Daily!$A:$A,"<"&DATE(VALUE(A30)+1,1,1)),"") | J30: =IF(OR(I30="",I29="",ROW()=2),"",LN(I30/I29))
A31: 2025 | B31: 1.0070184 | C31: 2.161382 | D31: =IF(OR(B31="",C31=""),"",B31-C31) | E31: 2.1230942 | G31: =IF(OR(E31="",F31=""),"",E31-F31) | H31: 6.5720704 | I31: =IFERROR(AVERAGEIFS(Daily!$B:$B,Daily!$A:$A,">="&DATE(VALUE(A31),12,1),Daily!$A:$A,"<"&DATE(VALUE(A31)+1,1,1)),"") | J31: =IF(OR(I31="",I30="",ROW()=2),"",LN(I31/I30))
A33: R² vs. USD/KRW change | D33: =IFERROR(RSQ($J$3:$J$31,D3:D31),"n/a") | G33: =IFERROR(RSQ($J$3:$J$31,G3:G31),"n/a") | H33: =IFERROR(RSQ($J$3:$J$31,H3:H31),"n/a")
A34: Descriptive only: same-year macro data are published after the fact. Blank cells (e.g. unpublished years) are skipped.

Sheet Flows_Daily
A1: Date | B1: KOSPI foreign net (KRW bn) | C1: KOSDAQ foreign net (KRW bn) | D1: Total (KRW bn) | E1: Cumulative 20D
A2: 38355 | B2: 99.474157 | C2: 3.4863644 | D2: =SUM(B2:C2)
A3: 38356 | B3: 39.672472 | C3: 4.2640971 | D3: =SUM(B3:C3)
A4: 38357 | B4: 24.585836 | C4: -6.5253902 | D4: =SUM(B4:C4)
A5: 38358 | B5: -0.5875336 | C5: 12.541011 | D5: =SUM(B5:C5)
A6: 38359 | B6: 17.806358 | C6: 30.49063 | D6: =SUM(B6:C6)
A7: 38362 | B7: 43.972562 | C7: -7.4926499 | D7: =SUM(B7:C7)
A8: 38363 | B8: -3.487909 | C8: 3.1066521 | D8: =SUM(B8:C8)
A9: 38364 | B9: 96.608337 | C9: -1.5968388 | D9: =SUM(B9:C9)
A10: 38365 | B10: -26.874392 | C10: -14.876875 | D10: =SUM(B10:C10)
A11: 38366 | B11: 189.23808 | C11: -0.91927587 | D11: =SUM(B11:C11)
A12: 38369 | B12: 327.30474 | C12: -2.2185222 | D12: =SUM(B12:C12)
A13: 38370 | B13: 104.74656 | C13: -3.2890757 | D13: =SUM(B13:C13)
... A20: 38379 | B20: 26.028936 | C20: -2.1030514 | D20: =SUM(B20:C20)
A21: 38380 | B21: -74.524693 | C21: -0.53865303 | D21: =SUM(B21:C21) | E21: =SUM(D2:D21)
A22: 38383 | B22: -46.800916 | C22: -37.965881 | D22: =SUM(B22:C22) | E22: =SUM(D3:D22)
A23: 38384 | B23: 95.488462 | C23: -9.3954942 | D23: =SUM(B23:C23) | E23: =SUM(D4:D23)
A24: 38385 | B24: -33.631341 | C24: -12.50431 | D24: =SUM(B24:C24) | E24: =SUM(D5:D24)
A25: 38386 | B25: 40.164172 | C25: 1.3885105 | D25: =SUM(B25:C25) | E25: =SUM(D6:D25)
A26: 38387 | B26: -3.0719288 | C26: -2.7350089 | D26: =SUM(B26:C26) | E26: =SUM(D7:D26)
A27: 38390 | B27: 179.28898 | C27: 9.6286203 | D27: =SUM(B27:C27) | E27: =SUM(D8:D27)
A28: 38394 | B28: 100.41072 | C28: 27.658815 | D28: =SUM(B28:C28) | E28: =SUM(D9:D28)
A29: 38397 | B29: 91.305521 | C29: 8.6424061 | D29: =SUM(B29:C29) | E29: =SUM(D10:D29)
A30: 38398 | B30: 105.33936 | C30: -4.9560704 | D30: =SUM(B30:C30) | E30: =SUM(D11:D30)
A31: 38399 | B31: 119.53734 | C31: -4.6282429 | D31: =SUM(B31:C31) | E31: =SUM(D12:D31)
A32: 38400 | B32: 47.386859 | C32: -7.9771052 | D32: =SUM(B32:C32) | E32: =SUM(D13:D32)
... A5371: 46307 | B5371: -2008.1924 | C5371: -24.863118 | D5371: =SUM(B5371:C5371) | E5371: =SUM(D5352:D5371)

Sheet Flows_Monthly
A1: Korea FX flows (US$ mn)
A2: Basic balance = current account + inward - outward investment (direct + portfolio, BPM6).
A4: Month | B4: Current account | C4: Goods | D4: Direct inv. assets (out) | E4: Direct inv. liab. (in) | F4: Portfolio assets (out) | G4: Portfolio liab. (in) | H4: Residents' outward inv. | I4: Foreigners' inward inv. | J4: Basic balance | K4: Foreign equity net buy | L4: USD/KRW avg | M4: USD/KRW month-end | N4: KRW chg 1M (log) | O4: Rate gap (pts) | P4: Chg in rate gap | Q4: Current acct 12M | R4: Outward inv. 12M | S4: Inward inv. 12M | T4: Basic balance 12M | U4: Foreign equity 12M | V4: KRW chg 12M (log) | X4: USD/KRW change vs. flows: one-variable regressions
A5: 34700 | B5: -1208.9 | D5: 225.5 | E5: 160.2 | F5: 209.8 | G5: 422.6 | H5: =IF(COUNT(D5,F5)<2,"",D5+F5) | I5: =IF(COUNT(E5,G5)<2,"",E5+G5) | J5: =IF(COUNT(B5,H5,I5)<3,"",B5+I5-H5) | K5: =IF(COUNTIFS(Flows_Daily!$A$2:$A$5371,">="&A5,Flows_Daily!$A$2:$A$5371,"<"&EDATE(A5,1))=0,"",SUMIFS(Flows_Daily!$D$2:$D$5371,Flows_Daily!$A$2:$A$5371,">="&A5,Flows_Daily!$A$2:$A$5371,"<"&EDATE(A5,1))*1000/L5) | L5: =IFERROR(AVERAGEIFS(Daily!$B:$B,Daily!$A:$A,">="&A5,Daily!$A:$A,"<"&EDATE(A5,1)),"") | M5: =IFERROR(INDEX(Daily!$B:$B,MATCH(EDATE(A5,1)-1,Daily!$A:$A,1)),"") | O5: =IFERROR(INDEX(Rates_Monthly!$D:$D,MATCH(A5,Rates_Monthly!$A:$A,0)),"") | X5: Driver | Y5: Months | Z5: Correlation | AA5: R² | AB5: KRW chg per $10bn
A6: 34731 | B6: -1522.1 | D6: 258.1 | E6: 122.9 | F6: 99.8 | G6: 390.2 | H6: =IF(COUNT(D6,F6)<2,"",D6+F6) | I6: =IF(COUNT(E6,G6)<2,"",E6+G6) | J6: =IF(COUNT(B6,H6,I6)<3,"",B6+I6-H6) | K6: =IF(COUNTIFS(Flows_Daily!$A$2:$A$5371,">="&A6,Flows_Daily!$A$2:$A$5371,"<"&EDATE(A6,1))=0,"",SUMIFS(Flows_Daily!$D$2:$D$5371,Flows_Daily!$A$2:$A$5371,">="&A6,Flows_Daily!$A$2:$A$5371,"<"&EDATE(A6,1))*1000/L6) | L6: =IFERROR(AVERAGEIFS(Daily!$B:$B,Daily!$A:$A,">="&A6,Daily!$A:$A,"<"&EDATE(A6,1)),"") | M6: =IFERROR(INDEX(Daily!$B:$B,MATCH(EDATE(A6,1)-1,Daily!$A:$A,1)),"") | N6: =IF(OR(M6="",M5=""),"",LN(M6/M5)) | O6: =IFERROR(INDEX(Rates_Monthly!$D:$D,MATCH(A6,Rates_Monthly!$A:$A,0)),"") | P6: =IF(OR(O6="",O5=""),"",O6-O5) | X6: 1M: change in rate gap (per 1 pt) | Y6: =SUMPRODUCT(ISNUMBER($P$6:$P$386)*ISNUMBER($N$6:$N$386)) | Z6: =IF(Y6<12,"n/a",CORREL($N$6:$N$386,$P$6:$P$386)) | AA6: =IF(Y6<12,"n/a",RSQ($N$6:$N$386,$P$6:$P$386)) | AB6: =IF(Y6<12,"n/a",SLOPE($N$6:$N$386,$P$6:$P$386)*1)
A7: 34759 | B7: -1562.3 | D7: 405 | E7: 115.8 | F7: 208.6 | G7: 1055.6 | H7: =IF(COUNT(D7,F7)<2,"",D7+F7) | I7: =IF(COUNT(E7,G7)<2,"",E7+G7) | J7: =IF(COUNT(B7,H7,I7)<3,"",B7+I7-H7) | K7: =IF(COUNTIFS(Flows_Daily!$A$2:$A$5371,">="&A7,Flows_Daily!$A$2:$A$5371,"<"&EDATE(A7,1))=0,"",SUMIFS(Flows_Daily!$D$2:$D$5371,Flows_Daily!$A$2:$A$5371,">="&A7,Flows_Daily!$A$2:$A$5371,"<"&EDATE(A7,1))*1000/L7) | L7: =IFERROR(AVERAGEIFS(Daily!$B:$B,Daily!$A:$A,">="&A7,Daily!$A:$A,"<"&EDATE(A7,1)),"") | M7: =IFERROR(INDEX(Daily!$B:$B,MATCH(EDATE(A7,1)-1,Daily!$A:$A,1)),"") | N7: =IF(OR(M7="",M6=""),"",LN(M7/M6)) | O7: =IFERROR(INDEX(Rates_Monthly!$D:$D,MATCH(A7,Rates_Monthly!$A:$A,0)),"") | P7: =IF(OR(O7="",O6=""),"",O7-O6) | X7: 1M: current account | Y7: =SUMPRODUCT(ISNUMBER($B$6:$B$386)*ISNUMBER($N$6:$N$386)) | Z7: =IF(Y7<12,"n/a",CORREL($N$6:$N$386,$B$6:$B$386)) | AA7: =IF(Y7<12,"n/a",RSQ($N$6:$N$386,$B$6:$B$386)) | AB7: =IF(Y7<12,"n/a",SLOPE($N$6:$N$386,$B$6:$B$386)*10000)
A8: 34790 | B8: -747.8 | D8: 425.9 | E8: 387.5 | F8: 263.7 | G8: 1019.8 | H8: =IF(COUNT(D8,F8)<2,"",D8+F8) | I8: =IF(COUNT(E8,G8)<2,"",E8+G8) | J8: =IF(COUNT(B8,H8,I8)<3,"",B8+I8-H8) | K8: =IF(COUNTIFS(Flows_Daily!$A$2:$A$5371,">="&A8,Flows_Daily!$A$2:$A$5371,"<"&EDATE(A8,1))=0,"",SUMIFS(Flows_Daily!$D$2:$D$5371,Flows_Daily!$A$2:$A$5371,">="&A8,Flows_Daily!$A$2:$A$5371,"<"&EDATE(A8,1))*1000/L8) | L8: =IFERROR(AVERAGEIFS(Daily!$B:$B,Daily!$A:$A,">="&A8,Daily!$A:$A,"<"&EDATE(A8,1)),"") | M8: =IFERROR(INDEX(Daily!$B:$B,MATCH(EDATE(A8,1)-1,Daily!$A:$A,1)),"") | N8: =IF(OR(M8="",M7=""),"",LN(M8/M7)) | O8: =IFERROR(INDEX(Rates_Monthly!$D:$D,MATCH(A8,Rates_Monthly!$A:$A,0)),"") | P8: =IF(OR(O8="",O7=""),"",O8-O7) | X8: 1M: residents' outward investment | Y8: =SUMPRODUCT(ISNUMBER($H$6:$H$386)*ISNUMBER($N$6:$N$386)) | Z8: =IF(Y8<12,"n/a",CORREL($N$6:$N$386,$H$6:$H$386)) | AA8: =IF(Y8<12,"n/a",RSQ($N$6:$N$386,$H$6:$H$386)) | AB8: =IF(Y8<12,"n/a",SLOPE($N$6:$N$386,$H$6:$H$386)*10000)
A9: 34820 | B9: -959.3 | D9: 203.5 | E9: 215.3 | F9: 495.3 | G9: 1277.5 | H9: =IF(COUNT(D9,F9)<2,"",D9+F9) | I9: =IF(COUNT(E9,G9)<2,"",E9+G9) | J9: =IF(COUNT(B9,H9,I9)<3,"",B9+I9-H9) | K9: =IF(COUNTIFS(Flows_Daily!$A$2:$A$5371,">="&A9,Flows_Daily!$A$2:$A$5371,"<"&EDATE(A9,1))=0,"",SUMIFS(Flows_Daily!$D$2:$D$5371,Flows_Daily!$A$2:$A$5371,">="&A9,Flows_Daily!$A$2:$A$5371,"<"&EDATE(A9,1))*1000/L9) | L9: =IFERROR(AVERAGEIFS(Daily!$B:$B,Daily!$A:$A,">="&A9,Daily!$A:$A,"<"&EDATE(A9,1)),"") | M9: =IFERROR(INDEX(Daily!$B:$B,MATCH(EDATE(A9,1)-1,Daily!$A:$A,1)),"") | N9: =IF(OR(M9="",M8=""),"",LN(M9/M8)) | O9: =IFERROR(INDEX(Rates_Monthly!$D:$D,MATCH(A9,Rates_Monthly!$A:$A,0)),"") | P9: =IF(OR(O9="",O8=""),"",O9-O8) | X9: 1M: foreigners' inward investment | Y9: =SUMPRODUCT(ISNUMBER($I$6:$I$386)*ISNUMBER($N$6:$N$386)) | Z9: =IF(Y9<12,"n/a",CORREL($N$6:$N$386,$I$6:$I$386)) | AA9: =IF(Y9<12,"n/a",RSQ($N$6:$N$386,$I$6:$I$386)) | AB9: =IF(Y9<12,"n/a",SLOPE($N$6:$N$386,$I$6:$I$386)*10000)
A10: 34851 | B10: -969.9 | D10: 270.3 | E10: 185.9 | F10: 389.5 | G10: 1211.5 | H10: =IF(COUNT(D10,F10)<2,"",D10+F10) | I10: =IF(COUNT(E10,G10)<2,"",E10+G10) | J10: =IF(COUNT(B10,H10,I10)<3,"",B10+I10-H10) | K10: =IF(COUNTIFS(Flows_Daily!$A$2:$A$5371,">="&A10,Flows_Daily!$A$2:$A$5371,"<"&EDATE(A10,1))=0,"",SUMIFS(Flows_Daily!$D$2:$D$5371,Flows_Daily!$A$2:$A$5371,">="&A10,Flows_Daily!$A$2:$A$5371,"<"&EDATE(A10,1))*1000/L10) | L10: =IFERROR(AVERAGEIFS(Daily!$B:$B,Daily!$A:$A,">="&A10,Daily!$A:$A,"<"&EDATE(A10,1)),"") | M10: =IFERROR(INDEX(Daily!$B:$B,MATCH(EDATE(A10,1)-1,Daily!$A:$A,1)),"") | N10: =IF(OR(M10="",M9=""),"",LN(M10/M9)) | O10: =IFERROR(INDEX(Rates_Monthly!$D:$D,MATCH(A10,Rates_Monthly!$A:$A,0)),"") | P10: =IF(OR(O10="",O9=""),"",O10-O9) | X10: 1M: basic balance | Y10: =SUMPRODUCT(ISNUMBER($J$6:$J$386)*ISNUMBER($N$6:$N$386)) | Z10: =IF(Y10<12,"n/a",CORREL($N$6:$N$386,$J$6:$J$386)) | AA10: =IF(Y10<12,"n/a",RSQ($N$6:$N$386,$J$6:$J$386)) | AB10: =IF(Y10<12,"n/a",SLOPE($N$6:$N$386,$J$6:$J$386)*10000)
A11: 34881 | B11: -491.7 | D11: 300.5 | E11: 208.7 | F11: 306.7 | G11: 2295.1 | H11: =IF(COUNT(D11,F11)<2,"",D11+F11) | I11: =IF(COUNT(E11,G11)<2,"",E11+G11) | J11: =IF(COUNT(B11,H11,I11)<3,"",B11+I11-H11) | K11: =IF(COUNTIFS(Flows_Daily!$A$2:$A$5371,">="&A11,Flows_Daily!$A$2:$A$5371,"<"&EDATE(A11,1))=0,"",SUMIFS(Flows_Daily!$D$2:$D$5371,Flows_Daily!$A$2:$A$5371,">="&A11,Flows_Daily!$A$2:$A$5371,"<"&EDATE(A11,1))*1000/L11) | L11: =IFERROR(AVERAGEIFS(Daily!$B:$B,Daily!$A:$A,">="&A11,Daily!$A:$A,"<"&EDATE(A11,1)),"") | M11: =IFERROR(INDEX(Daily!$B:$B,MATCH(EDATE(A11,1)-1,Daily!$A:$A,1)),"") | N11: =IF(OR(M11="",M10=""),"",LN(M11/M10)) | O11: =IFERROR(INDEX(Rates_Monthly!$D:$D,MATCH(A11,Rates_Monthly!$A:$A,0)),"") | P11: =IF(OR(O11="",O10=""),"",O11-O10) | X11: 1M: foreign equity net buying | Y11: =SUMPRODUCT(ISNUMBER($K$6:$K$386)*ISNUMBER($N$6:$N$386)) | Z11: =IF(Y11<12,"n/a",CORREL($N$6:$N$386,$K$6:$K$386)) | AA11: =IF(Y11<12,"n/a",RSQ($N$6:$N$386,$K$6:$K$386)) | AB11: =IF(Y11<12,"n/a",SLOPE($N$6:$N$386,$K$6:$K$386)*10000)
A12: 34912 | B12: -1313.9 | D12: 377.4 | E12: 111 | F12: 139.5 | G12: 1759.2 | H12: =IF(COUNT(D12,F12)<2,"",D12+F12) | I12: =IF(COUNT(E12,G12)<2,"",E12+G12) | J12: =IF(COUNT(B12,H12,I12)<3,"",B12+I12-H12) | K12: =IF(COUNTIFS(Flows_Daily!$A$2:$A$5371,">="&A12,Flows_Daily!$A$2:$A$5371,"<"&EDATE(A12,1))=0,"",SUMIFS(Flows_Daily!$D$2:$D$5371,Flows_Daily!$A$2:$A$5371,">="&A12,Flows_Daily!$A$2:$A$5371,"<"&EDATE(A12,1))*1000/L12) | L12: =IFERROR(AVERAGEIFS(Daily!$B:$B,Daily!$A:$A,">="&A12,Daily!$A:$A,"<"&EDATE(A12,1)),"") | M12: =IFERROR(INDEX(Daily!$B:$B,MATCH(EDATE(A12,1)-1,Daily!$A:$A,1)),"") | N12: =IF(OR(M12="",M11=""),"",LN(M12/M11)) | O12: =IFERROR(INDEX(Rates_Monthly!$D:$D,MATCH(A12,Rates_Monthly!$A:$A,0)),"") | P12: =IF(OR(O12="",O11=""),"",O12-O11) | X12: 12M: current account | Y12: =SUMPRODUCT(ISNUMBER($Q$17:$Q$386)*ISNUMBER($V$17:$V$386)) | Z12: =IF(Y12<12,"n/a",CORREL($V$17:$V$386,$Q$17:$Q$386)) | AA12: =IF(Y12<12,"n/a",RSQ($V$17:$V$386,$Q$17:$Q$386)) | AB12: =IF(Y12<12,"n/a",SLOPE($V$17:$V$386,$Q$17:$Q$386)*10000)
A13: 34943 | B13: -1018.8 | D13: 248.6 | E13: 190.4 | F13: 277.7 | G13: 1647.9 | H13: =IF(COUNT(D13,F13)<2,"",D13+F13) | I13: =IF(COUNT(E13,G13)<2,"",E13+G13) | J13: =IF(COUNT(B13,H13,I13)<3,"",B13+I13-H13) | K13: =IF(COUNTIFS(Flows_Daily!$A$2:$A$5371,">="&A13,Flows_Daily!$A$2:$A$5371,"<"&EDATE(A13,1))=0,"",SUMIFS(Flows_Daily!$D$2:$D$5371,Flows_Daily!$A$2:$A$5371,">="&A13,Flows_Daily!$A$2:$A$5371,"<"&EDATE(A13,1))*1000/L13) | L13: =IFERROR(AVERAGEIFS(Daily!$B:$B,Daily!$A:$A,">="&A13,Daily!$A:$A,"<"&EDATE(A13,1)),"") | M13: =IFERROR(INDEX(Daily!$B:$B,MATCH(EDATE(A13,1)-1,Daily!$A:$A,1)),"") | N13: =IF(OR(M13="",M12=""),"",LN(M13/M12)) | O13: =IFERROR(INDEX(Rates_Monthly!$D:$D,MATCH(A13,Rates_Monthly!$A:$A,0)),"") | P13: =IF(OR(O13="",O12=""),"",O13-O12) | X13: 12M: outward investment | Y13: =SUMPRODUCT(ISNUMBER($R$17:$R$386)*ISNUMBER($V$17:$V$386)) | Z13: =IF(Y13<12,"n/a",CORREL($V$17:$V$386,$R$17:$R$386)) | AA13: =IF(Y13<12,"n/a",RSQ($V$17:$V$386,$R$17:$R$386)) | AB13: =IF(Y13<12,"n/a",SLOPE($V$17:$V$386,$R$17:$R$386)*10000)
A14: 34973 | B14: -295.9 | D14: 236.4 | E14: 230.6 | F14: 292.7 | G14: 1152.6 | H14: =IF(COUNT(D14,F14)<2,"",D14+F14) | I14: =IF(COUNT(E14,G14)<2,"",E14+G14) | J14: =IF(COUNT(B14,H14,I14)<3,"",B14+I14-H14) | K14: =IF(COUNTIFS(Flows_Daily!$A$2:$A$5371,">="&A14,Flows_Daily!$A$2:$A$5371,"<"&EDATE(A14,1))=0,"",SUMIFS(Flows_Daily!$D$2:$D$5371,Flows_Daily!$A$2:$A$5371,">="&A14,Flows_Daily!$A$2:$A$5371,"<"&EDATE(A14,1))*1000/L14) | L14: =IFERROR(AVERAGEIFS(Daily!$B:$B,Daily!$A:$A,">="&A14,Daily!$A:$A,"<"&EDATE(A14,1)),"") | M14: =IFERROR(INDEX(Daily!$B:$B,MATCH(EDATE(A14,1)-1,Daily!$A:$A,1)),"") | N14: =IF(OR(M14="",M13=""),"",LN(M14/M13)) | O14: =IFERROR(INDEX(Rates_Monthly!$D:$D,MATCH(A14,Rates_Monthly!$A:$A,0)),"") | P14: =IF(OR(O14="",O13=""),"",O14-O13) | X14: 12M: basic balance | Y14: =SUMPRODUCT(ISNUMBER($T$17:$T$386)*ISNUMBER($V$17:$V$386)) | Z14: =IF(Y14<12,"n/a",CORREL($V$17:$V$386,$T$17:$T$386)) | AA14: =IF(Y14<12,"n/a",RSQ($V$17:$V$386,$T$17:$T$386)) | AB14: =IF(Y14<12,"n/a",SLOPE($V$17:$V$386,$T$17:$T$386)*10000)
A15: 35004 | B15: -148.1 | D15: 618.2 | E15: 268 | F15: 180.7 | G15: 979.4 | H15: =IF(COUNT(D15,F15)<2,"",D15+F15) | I15: =IF(COUNT(E15,G15)<2,"",E15+G15) | J15: =IF(COUNT(B15,H15,I15)<3,"",B15+I15-H15) | K15: =IF(COUNTIFS(Flows_Daily!$A$2:$A$5371,">="&A15,Flows_Daily!$A$2:$A$5371,"<"&EDATE(A15,1))=0,"",SUMIFS(Flows_Daily!$D$2:$D$5371,Flows_Daily!$A$2:$A$5371,">="&A15,Flows_Daily!$A$2:$A$5371,"<"&EDATE(A15,1))*1000/L15) | L15: =IFERROR(AVERAGEIFS(Daily!$B:$B,Daily!$A:$A,">="&A15,Daily!$A:$A,"<"&EDATE(A15,1)),"") | M15: =IFERROR(INDEX(Daily!$B:$B,MATCH(EDATE(A15,1)-1,Daily!$A:$A,1)),"") | N15: =IF(OR(M15="",M14=""),"",LN(M15/M14)) | O15: =IFERROR(INDEX(Rates_Monthly!$D:$D,MATCH(A15,Rates_Monthly!$A:$A,0)),"") | P15: =IF(OR(O15="",O14=""),"",O15-O14) | X15: 12M: foreign equity net buying | Y15: =SUMPRODUCT(ISNUMBER($U$17:$U$386)*ISNUMBER($V$17:$V$386)) | Z15: =IF(Y15<12,"n/a",CORREL($V$17:$V$386,$U$17:$U$386)) | AA15: =IF(Y15<12,"n/a",RSQ($V$17:$V$386,$U$17:$U$386)) | AB15: =IF(Y15<12,"n/a",SLOPE($V$17:$V$386,$U$17:$U$386)*10000)
A16: 35034 | B16: 9 | D16: 299.1 | E16: 290.8 | F16: 43.3 | G16: 1407.9 | H16: =IF(COUNT(D16,F16)<2,"",D16+F16) | I16: =IF(COUNT(E16,G16)<2,"",E16+G16) | J16: =IF(COUNT(B16,H16,I16)<3,"",B16+I16-H16) | K16: =IF(COUNTIFS(Flows_Daily!$A$2:$A$5371,">="&A16,Flows_Daily!$A$2:$A$5371,"<"&EDATE(A16,1))=0,"",SUMIFS(Flows_Daily!$D$2:$D$5371,Flows_Daily!$A$2:$A$5371,">="&A16,Flows_Daily!$A$2:$A$5371,"<"&EDATE(A16,1))*1000/L16) | L16: =IFERROR(AVERAGEIFS(Daily!$B:$B,Daily!$A:$A,">="&A16,Daily!$A:$A,"<"&EDATE(A16,1)),"") | M16: =IFERROR(INDEX(Daily!$B:$B,MATCH(EDATE(A16,1)-1,Daily!$A:$A,1)),"") | N16: =IF(OR(M16="",M15=""),"",LN(M16/M15)) | O16: =IFERROR(INDEX(Rates_Monthly!$D:$D,MATCH(A16,Rates_Monthly!$A:$A,0)),"") | P16: =IF(OR(O16="",O15=""),"",O16-O15) | Q16: =IF(COUNT(B5:B16)<12,"",SUM(B5:B16)) | R16: =IF(COUNT(H5:H16)<12,"",SUM(H5:H16)) | S16: =IF(COUNT(I5:I16)<12,"",SUM(I5:I16)) | T16: =IF(COUNT(J5:J16)<12,"",SUM(J5:J16)) | U16: =IF(COUNT(K5:K16)<12,"",SUM(K5:K16))
A17: 35065 | B17: -2159.9 | D17: 902.2 | E17: 221.1 | F17: 220.9 | G17: 218.9 | H17: =IF(COUNT(D17,F17)<2,"",D17+F17) | I17: =IF(COUNT(E17,G17)<2,"",E17+G17) | J17: =IF(COUNT(B17,H17,I17)<3,"",B17+I17-H17) | K17: =IF(COUNTIFS(Flows_Daily!$A$2:$A$5371,">="&A17,Flows_Daily!$A$2:$A$5371,"<"&EDATE(A17,1))=0,"",SUMIFS(Flows_Daily!$D$2:$D$5371,Flows_Daily!$A$2:$A$5371,">="&A17,Flows_Daily!$A$2:$A$5371,"<"&EDATE(A17,1))*1000/L17) | L17: =IFERROR(AVERAGEIFS(Daily!$B:$B,Daily!$A:$A,">="&A17,Daily!$A:$A,"<"&EDATE(A17,1)),"") | M17: =IFERROR(INDEX(Daily!$B:$B,MATCH(EDATE(A17,1)-1,Daily!$A:$A,1)),"") | N17: =IF(OR(M17="",M16=""),"",LN(M17/M16)) | O17: =IFERROR(INDEX(Rates_Monthly!$D:$D,MATCH(A17,Rates_Monthly!$A:$A,0)),"") | P17: =IF(OR(O17="",O16=""),"",O17-O16) | Q17: =IF(COUNT(B6:B17)<12,"",SUM(B6:B17)) | R17: =IF(COUNT(H6:H17)<12,"",SUM(H6:H17)) | S17: =IF(COUNT(I6:I17)<12,"",SUM(I6:I17)) | T17: =IF(COUNT(J6:J17)<12,"",SUM(J6:J17)) | U17: =IF(COUNT(K6:K17)<12,"",SUM(K6:K17)) | V17: =IF(OR(M17="",M5=""),"",LN(M17/M5))
A18: 35096 | B18: -2030.7 | D18: 365.4 | E18: 123.4 | F18: 395.9 | G18: 1049.7 | H18: =IF(COUNT(D18,F18)<2,"",D18+F18) | I18: =IF(COUNT(E18,G18)<2,"",E18+G18) | J18: =IF(COUNT(B18,H18,I18)<3,"",B18+I18-H18) | K18: =IF(COUNTIFS(Flows_Daily!$A$2:$A$5371,">="&A18,Flows_Daily!$A$2:$A$5371,"<"&EDATE(A18,1))=0,"",SUMIFS(Flows_Daily!$D$2:$D$5371,Flows_Daily!$A$2:$A$5371,">="&A18,Flows_Daily!$A$2:$A$5371,"<"&EDATE(A18,1))*1000/L18) | L18: =IFERROR(AVERAGEIFS(Daily!$B:$B,Daily!$A:$A,">="&A18,Daily!$A:$A,"<"&EDATE(A18,1)),"") | M18: =IFERROR(INDEX(Daily!$B:$B,MATCH(EDATE(A18,1)-1,Daily!$A:$A,1)),"") | N18: =IF(OR(M18="",M17=""),"",LN(M18/M17)) | O18: =IFERROR(INDEX(Rates_Monthly!$D:$D,MATCH(A18,Rates_Monthly!$A:$A,0)),"") | P18: =IF(OR(O18="",O17=""),"",O18-O17) | Q18: =IF(COUNT(B7:B18)<12,"",SUM(B7:B18)) | R18: =IF(COUNT(H7:H18)<12,"",SUM(H7:H18)) | S18: =IF(COUNT(I7:I18)<12,"",SUM(I7:I18)) | T18: =IF(COUNT(J7:J18)<12,"",SUM(J7:J18)) | U18: =IF(COUNT(K7:K18)<12,"",SUM(K7:K18)) | V18: =IF(OR(M18="",M6=""),"",LN(M18/M6)) | X18: KRW change > 0 = weaker won. A negative slope means more of that flow goes with a stronger won.
A19: 35125 | B19: -1687.8 | D19: 388.7 | E19: 150.6 | F19: 361.2 | G19: 1870.2 | H19: =IF(COUNT(D19,F19)<2,"",D19+F19) | I19: =IF(COUNT(E19,G19)<2,"",E19+G19) | J19: =IF(COUNT(B19,H19,I19)<3,"",B19+I19-H19) | K19: =IF(COUNTIFS(Flows_Daily!$A$2:$A$5371,">="&A19,Flows_Daily!$A$2:$A$5371,"<"&EDATE(A19,1))=0,"",SUMIFS(Flows_Daily!$D$2:$D$5371,Flows_Daily!$A$2:$A$5371,">="&A19,Flows_Daily!$A$2:$A$5371,"<"&EDATE(A19,1))*1000/L19) | L19: =IFERROR(AVERAGEIFS(Daily!$B:$B,Daily!$A:$A,">="&A19,Daily!$A:$A,"<"&EDATE(A19,1)),"") | M19: =IFERROR(INDEX(Daily!$B:$B,MATCH(EDATE(A19,1)-1,Daily!$A:$A,1)),"") | N19: =IF(OR(M19="",M18=""),"",LN(M19/M18)) | O19: =IFERROR(INDEX(Rates_Monthly!$D:$D,MATCH(A19,Rates_Monthly!$A:$A,0)),"") | P19: =IF(OR(O19="",O18=""),"",O19-O18) | Q19: =IF(COUNT(B8:B19)<12,"",SUM(B8:B19)) | R19: =IF(COUNT(H8:H19)<12,"",SUM(H8:H19)) | S19: =IF(COUNT(I8:I19)<12,"",SUM(I8:I19)) | T19: =IF(COUNT(J8:J19)<12,"",SUM(J8:J19)) | U19: =IF(COUNT(K8:K19)<12,"",SUM(K8:K19)) | V19: =IF(OR(M19="",M7=""),"",LN(M19/M7)) | X19: Contemporaneous and descriptive: flows and prices are decided together, so this is association, not causation.
A20: 35156 | B20: -2148 | D20: 392.3 | E20: 223.5 | F20: 336.5 | G20: 2655.4 | H20: =IF(COUNT(D20,F20)<2,"",D20+F20) | I20: =IF(COUNT(E20,G20)<2,"",E20+G20) | J20: =IF(COUNT(B20,H20,I20)<3,"",B20+I20-H20) | K20: =IF(COUNTIFS(Flows_Daily!$A$2:$A$5371,">="&A20,Flows_Daily!$A$2:$A$5371,"<"&EDATE(A20,1))=0,"",SUMIFS(Flows_Daily!$D$2:$D$5371,Flows_Daily!$A$2:$A$5371,">="&A20,Flows_Daily!$A$2:$A$5371,"<"&EDATE(A20,1))*1000/L20) | L20: =IFERROR(AVERAGEIFS(Daily!$B:$B,Daily!$A:$A,">="&A20,Daily!$A:$A,"<"&EDATE(A20,1)),"") | M20: =IFERROR(INDEX(Daily!$B:$B,MATCH(EDATE(A20,1)-1,Daily!$A:$A,1)),"") | N20: =IF(OR(M20="",M19=""),"",LN(M20/M19)) | O20: =IFERROR(INDEX(Rates_Monthly!$D:$D,MATCH(A20,Rates_Monthly!$A:$A,0)),"") | P20: =IF(OR(O20="",O19=""),"",O20-O19) | Q20: =IF(COUNT(B9:B20)<12,"",SUM(B9:B20)) | R20: =IF(COUNT(H9:H20)<12,"",SUM(H9:H20)) | S20: =IF(COUNT(I9:I20)<12,"",SUM(I9:I20)) | T20: =IF(COUNT(J9:J20)<12,"",SUM(J9:J20)) | U20: =IF(COUNT(K9:K20)<12,"",SUM(K9:K20)) | V20: =IF(OR(M20="",M8=""),"",LN(M20/M8)) | X20: 12M rows use overlapping windows, which overstates R² and the effective number of observations.
A21: 35186 | B21: -1687.2 | D21: 373.8 | E21: 254.9 | F21: 379.3 | G21: 1904.1 | H21: =IF(COUNT(D21,F21)<2,"",D21+F21) | I21: =IF(COUNT(E21,G21)<2,"",E21+G21) | J21: =IF(COUNT(B21,H21,I21)<3,"",B21+I21-H21) | K21: =IF(COUNTIFS(Flows_Daily!$A$2:$A$5371,">="&A21,Flows_Daily!$A$2:$A$5371,"<"&EDATE(A21,1))=0,"",SUMIFS(Flows_Daily!$D$2:$D$5371,Flows_Daily!$A$2:$A$5371,">="&A21,Flows_Daily!$A$2:$A$5371,"<"&EDATE(A21,1))*1000/L21) | L21: =IFERROR(AVERAGEIFS(Daily!$B:$B,Daily!$A:$A,">="&A21,Daily!$A:$A,"<"&EDATE(A21,1)),"") | M21: =IFERROR(INDEX(Daily!$B:$B,MATCH(EDATE(A21,1)-1,Daily!$A:$A,1)),"") | N21: =IF(OR(M21="",M20=""),"",LN(M21/M20)) | O21: =IFERROR(INDEX(Rates_Monthly!$D:$D,MATCH(A21,Rates_Monthly!$A:$A,0)),"") | P21: =IF(OR(O21="",O20=""),"",O21-O20) | Q21: =IF(COUNT(B10:B21)<12,"",SUM(B10:B21)) | R21: =IF(COUNT(H10:H21)<12,"",SUM(H10:H21)) | S21: =IF(COUNT(I10:I21)<12,"",SUM(I10:I21)) | T21: =IF(COUNT(J10:J21)<12,"",SUM(J10:J21)) | U21: =IF(COUNT(K10:K21)<12,"",SUM(K10:K21)) | V21: =IF(OR(M21="",M9=""),"",LN(M21/M9)) | X21: BoP figures are published about 5 weeks after month-end; foreign equity flows are same-day.
A22: 35217 | B22: -1473.2 | D22: 350.1 | E22: 439.4 | F22: 180.9 | G22: 2072.6 | H22: =IF(COUNT(D22,F22)<2,"",D22+F22) | I22: =IF(COUNT(E22,G22)<2,"",E22+G22) | J22: =IF(COUNT(B22,H22,I22)<3,"",B22+I22-H22) | K22: =IF(COUNTIFS(Flows_Daily!$A$2:$A$5371,">="&A22,Flows_Daily!$A$2:$A$5371,"<"&EDATE(A22,1))=0,"",SUMIFS(Flows_Daily!$D$2:$D$5371,Flows_Daily!$A$2:$A$5371,">="&A22,Flows_Daily!$A$2:$A$5371,"<"&EDATE(A22,1))*1000/L22) | L22: =IFERROR(AVERAGEIFS(Daily!$B:$B,Daily!$A:$A,">="&A22,Daily!$A:$A,"<"&EDATE(A22,1)),"") | M22: =IFERROR(INDEX(Daily!$B:$B,MATCH(EDATE(A22,1)-1,Daily!$A:$A,1)),"") | N22: =IF(OR(M22="",M21=""),"",LN(M22/M21)) | O22: =IFERROR(INDEX(Rates_Monthly!$D:$D,MATCH(A22,Rates_Monthly!$A:$A,0)),"") | P22: =IF(OR(O22="",O21=""),"",O22-O21) | Q22: =IF(COUNT(B11:B22)<12,"",SUM(B11:B22)) | R22: =IF(COUNT(H11:H22)<12,"",SUM(H11:H22)) | S22: =IF(COUNT(I11:I22)<12,"",SUM(I11:I22)) | T22: =IF(COUNT(J11:J22)<12,"",SUM(J11:J22)) | U22: =IF(COUNT(K11:K22)<12,"",SUM(K11:K22)) | V22: =IF(OR(M22="",M10=""),"",LN(M22/M10))
A23: 35247 | B23: -2051.2 | D23: 232 | E23: 46.2 | F23: 411.6 | G23: 1790.3 | H23: =IF(COUNT(D23,F23)<2,"",D23+F23) | I23: =IF(COUNT(E23,G23)<2,"",E23+G23) | J23: =IF(COUNT(B23,H23,I23)<3,"",B23+I23-H23) | K23: =IF(COUNTIFS(Flows_Daily!$A$2:$A$5371,">="&A23,Flows_Daily!$A$2:$A$5371,"<"&EDATE(A23,1))=0,"",SUMIFS(Flows_Daily!$D$2:$D$5371,Flows_Daily!$A$2:$A$5371,">="&A23,Flows_Daily!$A$2:$A$5371,"<"&EDATE(A23,1))*1000/L23) | L23: =IFERROR(AVERAGEIFS(Daily!$B:$B,Daily!$A:$A,">="&A23,Daily!$A:$A,"<"&EDATE(A23,1)),"") | M23: =IFERROR(INDEX(Daily!$B:$B,MATCH(EDATE(A23,1)-1,Daily!$A:$A,1)),"") | N23: =IF(OR(M23="",M22=""),"",LN(M23/M22)) | O23: =IFERROR(INDEX(Rates_Monthly!$D:$D,MATCH(A23,Rates_Monthly!$A:$A,0)),"") | P23: =IF(OR(O23="",O22=""),"",O23-O22) | Q23: =IF(COUNT(B12:B23)<12,"",SUM(B12:B23)) | R23: =IF(COUNT(H12:H23)<12,"",SUM(H12:H23)) | S23: =IF(COUNT(I12:I23)<12,"",SUM(I12:I23)) | T23: =IF(COUNT(J12:J23)<12,"",SUM(J12:J23)) | U23: =IF(COUNT(K12:K23)<12,"",SUM(K12:K23)) | V23: =IF(OR(M23="",M11=""),"",LN(M23/M11))
A24: 35278 | B24: -3506.7 | D24: 359.3 | E24: 99.9 | F24: 882.3 | G24: 1875.5 | H24: =IF(COUNT(D24,F24)<2,"",D24+F24) | I24: =IF(COUNT(E24,G24)<2,"",E24+G24) | J24: =IF(COUNT(B24,H24,I24)<3,"",B24+I24-H24) | K24: =IF(COUNTIFS(Flows_Daily!$A$2:$A$5371,">="&A24,Flows_Daily!$A$2:$A$5371,"<"&EDATE(A24,1))=0,"",SUMIFS(Flows_Daily!$D$2:$D$5371,Flows_Daily!$A$2:$A$5371,">="&A24,Flows_Daily!$A$2:$A$5371,"<"&EDATE(A24,1))*1000/L24) | L24: =IFERROR(AVERAGEIFS(Daily!$B:$B,Daily!$A:$A,">="&A24,Daily!$A:$A,"<"&EDATE(A24,1)),"") | M24: =IFERROR(INDEX(Daily!$B:$B,MATCH(EDATE(A24,1)-1,Daily!$A:$A,1)),"") | N24: =IF(OR(M24="",M23=""),"",LN(M24/M23)) | O24: =IFERROR(INDEX(Rates_Monthly!$D:$D,MATCH(A24,Rates_Monthly!$A:$A,0)),"") | P24: =IF(OR(O24="",O23=""),"",O24-O23) | Q24: =IF(COUNT(B13:B24)<12,"",SUM(B13:B24)) | R24: =IF(COUNT(H13:H24)<12,"",SUM(H13:H24)) | S24: =IF(COUNT(I13:I24)<12,"",SUM(I13:I24)) | T24: =IF(COUNT(J13:J24)<12,"",SUM(J13:J24)) | U24: =IF(COUNT(K13:K24)<12,"",SUM(K13:K24)) | V24: =IF(OR(M24="",M12=""),"",LN(M24/M12))
A25: 35309 | B25: -1203.2 | D25: 310.9 | E25: 113.1 | F25: 657.4 | G25: 1530.7 | H25: =IF(COUNT(D25,F25)<2,"",D25+F25) | I25: =IF(COUNT(E25,G25)<2,"",E25+G25) | J25: =IF(COUNT(B25,H25,I25)<3,"",B25+I25-H25) | K25: =IF(COUNTIFS(Flows_Daily!$A$2:$A$5371,">="&A25,Flows_Daily!$A$2:$A$5371,"<"&EDATE(A25,1))=0,"",SUMIFS(Flows_Daily!$D$2:$D$5371,Flows_Daily!$A$2:$A$5371,">="&A25,Flows_Daily!$A$2:$A$5371,"<"&EDATE(A25,1))*1000/L25) | L25: =IFERROR(AVERAGEIFS(Daily!$B:$B,Daily!$A:$A,">="&A25,Daily!$A:$A,"<"&EDATE(A25,1)),"") | M25: =IFERROR(INDEX(Daily!$B:$B,MATCH(EDATE(A25,1)-1,Daily!$A:$A,1)),"") | N25: =IF(OR(M25="",M24=""),"",LN(M25/M24)) | O25: =IFERROR(INDEX(Rates_Monthly!$D:$D,MATCH(A25,Rates_Monthly!$A:$A,0)),"") | P25: =IF(OR(O25="",O24=""),"",O25-O24) | Q25: =IF(COUNT(B14:B25)<12,"",SUM(B14:B25)) | R25: =IF(COUNT(H14:H25)<12,"",SUM(H14:H25)) | S25: =IF(COUNT(I14:I25)<12,"",SUM(I14:I25)) | T25: =IF(COUNT(J14:J25)<12,"",SUM(J14:J25)) | U25: =IF(COUNT(K14:K25)<12,"",SUM(K14:K25)) | V25: =IF(OR(M25="",M13=""),"",LN(M25/M13))
A26: 35339 | B26: -2493.7 | D26: 354.7 | E26: 219 | F26: 923.9 | G26: 1863.5 | H26: =IF(COUNT(D26,F26)<2,"",D26+F26) | I26: =IF(COUNT(E26,G26)<2,"",E26+G26) | J26: =IF(COUNT(B26,H26,I26)<3,"",B26+I26-H26) | K26: =IF(COUNTIFS(Flows_Daily!$A$2:$A$5371,">="&A26,Flows_Daily!$A$2:$A$5371,"<"&EDATE(A26,1))=0,"",SUMIFS(Flows_Daily!$D$2:$D$5371,Flows_Daily!$A$2:$A$5371,">="&A26,Flows_Daily!$A$2:$A$5371,"<"&EDATE(A26,1))*1000/L26) | L26: =IFERROR(AVERAGEIFS(Daily!$B:$B,Daily!$A:$A,">="&A26,Daily!$A:$A,"<"&EDATE(A26,1)),"") | M26: =IFERROR(INDEX(Daily!$B:$B,MATCH(EDATE(A26,1)-1,Daily!$A:$A,1)),"") | N26: =IF(OR(M26="",M25=""),"",LN(M26/M25)) | O26: =IFERROR(INDEX(Rates_Monthly!$D:$D,MATCH(A26,Rates_Monthly!$A:$A,0)),"") | P26: =IF(OR(O26="",O25=""),"",O26-O25) | Q26: =IF(COUNT(B15:B26)<12,"",SUM(B15:B26)) | R26: =IF(COUNT(H15:H26)<12,"",SUM(H15:H26)) | S26: =IF(COUNT(I15:I26)<12,"",SUM(I15:I26)) | T26: =IF(COUNT(J15:J26)<12,"",SUM(J15:J26)) | U26: =IF(COUNT(K15:K26)<12,"",SUM(K15:K26)) | V26: =IF(OR(M26="",M14=""),"",LN(M26/M14))
A27: 35370 | B27: -2488 | D27: 334.3 | E27: 265.4 | F27: 969.2 | G27: 2682.3 | H27: =IF(COUNT(D27,F27)<2,"",D27+F27) | I27: =IF(COUNT(E27,G27)<2,"",E27+G27) | J27: =IF(COUNT(B27,H27,I27)<3,"",B27+I27-H27) | K27: =IF(COUNTIFS(Flows_Daily!$A$2:$A$5371,">="&A27,Flows_Daily!$A$2:$A$5371,"<"&EDATE(A27,1))=0,"",SUMIFS(Flows_Daily!$D$2:$D$5371,Flows_Daily!$A$2:$A$5371,">="&A27,Flows_Daily!$A$2:$A$5371,"<"&EDATE(A27,1))*1000/L27) | L27: =IFERROR(AVERAGEIFS(Daily!$B:$B,Daily!$A:$A,">="&A27,Daily!$A:$A,"<"&EDATE(A27,1)),"") | M27: =IFERROR(INDEX(Daily!$B:$B,MATCH(EDATE(A27,1)-1,Daily!$A:$A,1)),"") | N27: =IF(OR(M27="",M26=""),"",LN(M27/M26)) | O27: =IFERROR(INDEX(Rates_Monthly!$D:$D,MATCH(A27,Rates_Monthly!$A:$A,0)),"") | P27: =IF(OR(O27="",O26=""),"",O27-O26) | Q27: =IF(COUNT(B16:B27)<12,"",SUM(B16:B27)) | R27: =IF(COUNT(H16:H27)<12,"",SUM(H16:H27)) | S27: =IF(COUNT(I16:I27)<12,"",SUM(I16:I27)) | T27: =IF(COUNT(J16:J27)<12,"",SUM(J16:J27)) | U27: =IF(COUNT(K16:K27)<12,"",SUM(K16:K27)) | V27: =IF(OR(M27="",M15=""),"",LN(M27/M15))
A28: 35400 | B28: -1531.5 | D28: 589.6 | E28: 626.1 | F28: 693.5 | G28: 2001.2 | H28: =IF(COUNT(D28,F28)<2,"",D28+F28) | I28: =IF(COUNT(E28,G28)<2,"",E28+G28) | J28: =IF(COUNT(B28,H28,I28)<3,"",B28+I28-H28) | K28: =IF(COUNTIFS(Flows_Daily!$A$2:$A$5371,">="&A28,Flows_Daily!$A$2:$A$5371,"<"&EDATE(A28,1))=0,"",SUMIFS(Flows_Daily!$D$2:$D$5371,Flows_Daily!$A$2:$A$5371,">="&A28,Flows_Daily!$A$2:$A$5371,"<"&EDATE(A28,1))*1000/L28) | L28: =IFERROR(AVERAGEIFS(Daily!$B:$B,Daily!$A:$A,">="&A28,Daily!$A:$A,"<"&EDATE(A28,1)),"") | M28: =IFERROR(INDEX(Daily!$B:$B,MATCH(EDATE(A28,1)-1,Daily!$A:$A,1)),"") | N28: =IF(OR(M28="",M27=""),"",LN(M28/M27)) | O28: =IFERROR(INDEX(Rates_Monthly!$D:$D,MATCH(A28,Rates_Monthly!$A:$A,0)),"") | P28: =IF(OR(O28="",O27=""),"",O28-O27) | Q28: =IF(COUNT(B17:B28)<12,"",SUM(B17:B28)) | R28: =IF(COUNT(H17:H28)<12,"",SUM(H17:H28)) | S28: =IF(COUNT(I17:I28)<12,"",SUM(I17:I28)) | T28: =IF(COUNT(J17:J28)<12,"",SUM(J17:J28)) | U28: =IF(COUNT(K17:K28)<12,"",SUM(K17:K28)) | V28: =IF(OR(M28="",M16=""),"",LN(M28/M16))
A29: 35431 | B29: -3490.7 | D29: 504.3 | E29: 75.8 | F29: 394.7 | G29: 843.9 | H29: =IF(COUNT(D29,F29)<2,"",D29+F29) | I29: =IF(COUNT(E29,G29)<2,"",E29+G29) | J29: =IF(COUNT(B29,H29,I29)<3,"",B29+I29-H29) | K29: =IF(COUNTIFS(Flows_Daily!$A$2:$A$5371,">="&A29,Flows_Daily!$A$2:$A$5371,"<"&EDATE(A29,1))=0,"",SUMIFS(Flows_Daily!$D$2:$D$5371,Flows_Daily!$A$2:$A$5371,">="&A29,Flows_Daily!$A$2:$A$5371,"<"&EDATE(A29,1))*1000/L29) | L29: =IFERROR(AVERAGEIFS(Daily!$B:$B,Daily!$A:$A,">="&A29,Daily!$A:$A,"<"&EDATE(A29,1)),"") | M29: =IFERROR(INDEX(Daily!$B:$B,MATCH(EDATE(A29,1)-1,Daily!$A:$A,1)),"") | N29: =IF(OR(M29="",M28=""),"",LN(M29/M28)) | O29: =IFERROR(INDEX(Rates_Monthly!$D:$D,MATCH(A29,Rates_Monthly!$A:$A,0)),"") | P29: =IF(OR(O29="",O28=""),"",O29-O28) | Q29: =IF(COUNT(B18:B29)<12,"",SUM(B18:B29)) | R29: =IF(COUNT(H18:H29)<12,"",SUM(H18:H29)) | S29: =IF(COUNT(I18:I29)<12,"",SUM(I18:I29)) | T29: =IF(COUNT(J18:J29)<12,"",SUM(J18:J29)) | U29: =IF(COUNT(K18:K29)<12,"",SUM(K18:K29)) | V29: =IF(OR(M29="",M17=""),"",LN(M29/M17))
A30: 35462 | B30: -3041.2 | D30: 199.2 | E30: 453.3 | F30: 525.8 | G30: 867.1 | H30: =IF(COUNT(D30,F30)<2,"",D30+F30) | I30: =IF(COUNT(E30,G30)<2,"",E30+G30) | J30: =IF(COUNT(B30,H30,I30)<3,"",B30+I30-H30) | K30: =IF(COUNTIFS(Flows_Daily!$A$2:$A$5371,">="&A30,Flows_Daily!$A$2:$A$5371,"<"&EDATE(A30,1))=0,"",SUMIFS(Flows_Daily!$D$2:$D$5371,Flows_Daily!$A$2:$A$5371,">="&A30,Flows_Daily!$A$2:$A$5371,"<"&EDATE(A30,1))*1000/L30) | L30: =IFERROR(AVERAGEIFS(Daily!$B:$B,Daily!$A:$A,">="&A30,Daily!$A:$A,"<"&EDATE(A30,1)),"") | M30: =IFERROR(INDEX(Daily!$B:$B,MATCH(EDATE(A30,1)-1,Daily!$A:$A,1)),"") | N30: =IF(OR(M30="",M29=""),"",LN(M30/M29)) | O30: =IFERROR(INDEX(Rates_Monthly!$D:$D,MATCH(A30,Rates_Monthly!$A:$A,0)),"") | P30: =IF(OR(O30="",O29=""),"",O30-O29) | Q30: =IF(COUNT(B19:B30)<12,"",SUM(B19:B30)) | R30: =IF(COUNT(H19:H30)<12,"",SUM(H19:H30)) | S30: =IF(COUNT(I19:I30)<12,"",SUM(I19:I30)) | T30: =IF(COUNT(J19:J30)<12,"",SUM(J19:J30)) | U30: =IF(COUNT(K19:K30)<12,"",SUM(K19:K30)) | V30: =IF(OR(M30="",M18=""),"",LN(M30/M18))
A31: 35490 | B31: -1162.8 | D31: 414.6 | E31: 250 | F31: -400.9 | G31: 1340.4 | H31: =IF(COUNT(D31,F31)<2,"",D31+F31) | I31: =IF(COUNT(E31,G31)<2,"",E31+G31) | J31: =IF(COUNT(B31,H31,I31)<3,"",B31+I31-H31) | K31: =IF(COUNTIFS(Flows_Daily!$A$2:$A$5371,">="&A31,Flows_Daily!$A$2:$A$5371,"<"&EDATE(A31,1))=0,"",SUMIFS(Flows_Daily!$D$2:$D$5371,Flows_Daily!$A$2:$A$5371,">="&A31,Flows_Daily!$A$2:$A$5371,"<"&EDATE(A31,1))*1000/L31) | L31: =IFERROR(AVERAGEIFS(Daily!$B:$B,Daily!$A:$A,">="&A31,Daily!$A:$A,"<"&EDATE(A31,1)),"") | M31: =IFERROR(INDEX(Daily!$B:$B,MATCH(EDATE(A31,1)-1,Daily!$A:$A,1)),"") | N31: =IF(OR(M31="",M30=""),"",LN(M31/M30)) | O31: =IFERROR(INDEX(Rates_Monthly!$D:$D,MATCH(A31,Rates_Monthly!$A:$A,0)),"") | P31: =IF(OR(O31="",O30=""),"",O31-O30) | Q31: =IF(COUNT(B20:B31)<12,"",SUM(B20:B31)) | R31: =IF(COUNT(H20:H31)<12,"",SUM(H20:H31)) | S31: =IF(COUNT(I20:I31)<12,"",SUM(I20:I31)) | T31: =IF(COUNT(J20:J31)<12,"",SUM(J20:J31)) | U31: =IF(COUNT(K20:K31)<12,"",SUM(K20:K31)) | V31: =IF(OR(M31="",M19=""),"",LN(M31/M19))
A32: 35521 | B32: -1852.2 | D32: 172.4 | E32: 409.1 | F32: 240.8 | G32: 1007.6 | H32: =IF(COUNT(D32,F32)<2,"",D32+F32) | I32: =IF(COUNT(E32,G32)<2,"",E32+G32) | J32: =IF(COUNT(B32,H32,I32)<3,"",B32+I32-H32) | K32: =IF(COUNTIFS(Flows_Daily!$A$2:$A$5371,">="&A32,Flows_Daily!$A$2:$A$5371,"<"&EDATE(A32,1))=0,"",SUMIFS(Flows_Daily!$D$2:$D$5371,Flows_Daily!$A$2:$A$5371,">="&A32,Flows_Daily!$A$2:$A$5371,"<"&EDATE(A32,1))*1000/L32) | L32: =IFERROR(AVERAGEIFS(Daily!$B:$B,Daily!$A:$A,">="&A32,Daily!$A:$A,"<"&EDATE(A32,1)),"") | M32: =IFERROR(INDEX(Daily!$B:$B,MATCH(EDATE(A32,1)-1,Daily!$A:$A,1)),"") | N32: =IF(OR(M32="",M31=""),"",LN(M32/M31)) | O32: =IFERROR(INDEX(Rates_Monthly!$D:$D,MATCH(A32,Rates_Monthly!$A:$A,0)),"") | P32: =IF(OR(O32="",O31=""),"",O32-O31) | Q32: =IF(COUNT(B21:B32)<12,"",SUM(B21:B32)) | R32: =IF(COUNT(H21:H32)<12,"",SUM(H21:H32)) | S32: =IF(COUNT(I21:I32)<12,"",SUM(I21:I32)) | T32: =IF(COUNT(J21:J32)<12,"",SUM(J21:J32)) | U32: =IF(COUNT(K21:K32)<12,"",SUM(K21:K32)) | V32: =IF(OR(M32="",M20=""),"",LN(M32/M20))
A33: 35551 | B33: -363.4 | D33: 400.6 | E33: 251.1 | F33: 105.9 | G33: 2129 | H33: =IF(COUNT(D33,F33)<2,"",D33+F33) | I33: =IF(COUNT(E33,G33)<2,"",E33+G33) | J33: =IF(COUNT(B33,H33,I33)<3,"",B33+I33-H33) | K33: =IF(COUNTIFS(Flows_Daily!$A$2:$A$5371,">="&A33,Flows_Daily!$A$2:$A$5371,"<"&EDATE(A33,1))=0,"",SUMIFS(Flows_Daily!$D$2:$D$5371,Flows_Daily!$A$2:$A$5371,">="&A33,Flows_Daily!$A$2:$A$5371,"<"&EDATE(A33,1))*1000/L33) | L33: =IFERROR(AVERAGEIFS(Daily!$B:$B,Daily!$A:$A,">="&A33,Daily!$A:$A,"<"&EDATE(A33,1)),"") | M33: =IFERROR(INDEX(Daily!$B:$B,MATCH(EDATE(A33,1)-1,Daily!$A:$A,1)),"") | N33: =IF(OR(M33="",M32=""),"",LN(M33/M32)) | O33: =IFERROR(INDEX(Rates_Monthly!$D:$D,MATCH(A33,Rates_Monthly!$A:$A,0)),"") | P33: =IF(OR(O33="",O32=""),"",O33-O32) | Q33: =IF(COUNT(B22:B33)<12,"",SUM(B22:B33)) | R33: =IF(COUNT(H22:H33)<12,"",SUM(H22:H33)) | S33: =IF(COUNT(I22:I33)<12,"",SUM(I22:I33)) | T33: =IF(COUNT(J22:J33)<12,"",SUM(J22:J33)) | U33: =IF(COUNT(K22:K33)<12,"",SUM(K22:K33)) | V33: =IF(OR(M33="",M21=""),"",LN(M33/M21))
... A384: 46235 | B384: 46113 | D384: 6216 | E384: -1608.7 | F384: 16595 | G384: -4847.7 | H384: =IF(COUNT(D384,F384)<2,"",D384+F384) | I384: =IF(COUNT(E384,G384)<2,"",E384+G384) | J384: =IF(COUNT(B384,H384,I384)<3,"",B384+I384-H384) | K384: =IF(COUNTIFS(Flows_Daily!$A$2:$A$5371,">="&A384,Flows_Daily!$A$2:$A$5371,"<"&EDATE(A384,1))=0,"",SUMIFS(Flows_Daily!$D$2:$D$5371,Flows_Daily!$A$2:$A$5371,">="&A384,Flows_Daily!$A$2:$A$5371,"<"&EDATE(A384,1))*1000/L384) | L384: =IFERROR(AVERAGEIFS(Daily!$B:$B,Daily!$A:$A,">="&A384,Daily!$A:$A,"<"&EDATE(A384,1)),"") | M384: =IFERROR(INDEX(Daily!$B:$B,MATCH(EDATE(A384,1)-1,Daily!$A:$A,1)),"") | N384: =IF(OR(M384="",M383=""),"",LN(M384/M383)) | O384: =IFERROR(INDEX(Rates_Monthly!$D:$D,MATCH(A384,Rates_Monthly!$A:$A,0)),"") | P384: =IF(OR(O384="",O383=""),"",O384-O383) | Q384: =IF(COUNT(B373:B384)<12,"",SUM(B373:B384)) | R384: =IF(COUNT(H373:H384)<12,"",SUM(H373:H384)) | S384: =IF(COUNT(I373:I384)<12,"",SUM(I373:I384)) | T384: =IF(COUNT(J373:J384)<12,"",SUM(J373:J384)) | U384: =IF(COUNT(K373:K384)<12,"",SUM(K373:K384)) | V384: =IF(OR(M384="",M372=""),"",LN(M384/M372))
A385: 46266 | H385: =IF(COUNT(D385,F385)<2,"",D385+F385) | I385: =IF(COUNT(E385,G385)<2,"",E385+G385) | J385: =IF(COUNT(B385,H385,I385)<3,"",B385+I385-H385) | K385: =IF(COUNTIFS(Flows_Daily!$A$2:$A$5371,">="&A385,Flows_Daily!$A$2:$A$5371,"<"&EDATE(A385,1))=0,"",SUMIFS(Flows_Daily!$D$2:$D$5371,Flows_Daily!$A$2:$A$5371,">="&A385,Flows_Daily!$A$2:$A$5371,"<"&EDATE(A385,1))*1000/L385) | L385: =IFERROR(AVERAGEIFS(Daily!$B:$B,Daily!$A:$A,">="&A385,Daily!$A:$A,"<"&EDATE(A385,1)),"") | M385: =IFERROR(INDEX(Daily!$B:$B,MATCH(EDATE(A385,1)-1,Daily!$A:$A,1)),"") | N385: =IF(OR(M385="",M384=""),"",LN(M385/M384)) | O385: =IFERROR(INDEX(Rates_Monthly!$D:$D,MATCH(A385,Rates_Monthly!$A:$A,0)),"") | P385: =IF(OR(O385="",O384=""),"",O385-O384) | Q385: =IF(COUNT(B374:B385)<12,"",SUM(B374:B385)) | R385: =IF(COUNT(H374:H385)<12,"",SUM(H374:H385)) | S385: =IF(COUNT(I374:I385)<12,"",SUM(I374:I385)) | T385: =IF(COUNT(J374:J385)<12,"",SUM(J374:J385)) | U385: =IF(COUNT(K374:K385)<12,"",SUM(K374:K385)) | V385: =IF(OR(M385="",M373=""),"",LN(M385/M373))
A386: 46296 | H386: =IF(COUNT(D386,F386)<2,"",D386+F386) | I386: =IF(COUNT(E386,G386)<2,"",E386+G386) | J386: =IF(COUNT(B386,H386,I386)<3,"",B386+I386-H386) | K386: =IF(COUNTIFS(Flows_Daily!$A$2:$A$5371,">="&A386,Flows_Daily!$A$2:$A$5371,"<"&EDATE(A386,1))=0,"",SUMIFS(Flows_Daily!$D$2:$D$5371,Flows_Daily!$A$2:$A$5371,">="&A386,Flows_Daily!$A$2:$A$5371,"<"&EDATE(A386,1))*1000/L386) | L386: =IFERROR(AVERAGEIFS(Daily!$B:$B,Daily!$A:$A,">="&A386,Daily!$A:$A,"<"&EDATE(A386,1)),"") | M386: =IFERROR(INDEX(Daily!$B:$B,MATCH(EDATE(A386,1)-1,Daily!$A:$A,1)),"") | N386: =IF(OR(M386="",M385=""),"",LN(M386/M385)) | O386: =IFERROR(INDEX(Rates_Monthly!$D:$D,MATCH(A386,Rates_Monthly!$A:$A,0)),"") | P386: =IF(OR(O386="",O385=""),"",O386-O385) | Q386: =IF(COUNT(B375:B386)<12,"",SUM(B375:B386)) | R386: =IF(COUNT(H375:H386)<12,"",SUM(H375:H386)) | S386: =IF(COUNT(I375:I386)<12,"",SUM(I375:I386)) | T386: =IF(COUNT(J375:J386)<12,"",SUM(J375:J386)) | U386: =IF(COUNT(K375:K386)<12,"",SUM(K375:K386)) | V386: =IF(OR(M386="",M374=""),"",LN(M386/M374))

Sheet Stress
A1: Largest daily moves in USD/KRW
A2: Log returns of the Fed H.10 daily rate. Ties return the first matching date.
A4: # | B4: Date | C4: Won weaker | E4: # | F4: Date | G4: Won stronger
A5: 1 | B5: =INDEX(Daily!$A$3:$A$7964,MATCH(C5,Daily!$C$3:$C$7964,0)) | C5: =LARGE(Daily!$C$3:$C$7964,A5) | E5: 1 | F5: =INDEX(Daily!$A$3:$A$7964,MATCH(G5,Daily!$C$3:$C$7964,0)) | G5: =SMALL(Daily!$C$3:$C$7964,E5)
A6: 2 | B6: =INDEX(Daily!$A$3:$A$7964,MATCH(C6,Daily!$C$3:$C$7964,0)) | C6: =LARGE(Daily!$C$3:$C$7964,A6) | E6: 2 | F6: =INDEX(Daily!$A$3:$A$7964,MATCH(G6,Daily!$C$3:$C$7964,0)) | G6: =SMALL(Daily!$C$3:$C$7964,E6)
A7: 3 | B7: =INDEX(Daily!$A$3:$A$7964,MATCH(C7,Daily!$C$3:$C$7964,0)) | C7: =LARGE(Daily!$C$3:$C$7964,A7) | E7: 3 | F7: =INDEX(Daily!$A$3:$A$7964,MATCH(G7,Daily!$C$3:$C$7964,0)) | G7: =SMALL(Daily!$C$3:$C$7964,E7)
A8: 4 | B8: =INDEX(Daily!$A$3:$A$7964,MATCH(C8,Daily!$C$3:$C$7964,0)) | C8: =LARGE(Daily!$C$3:$C$7964,A8) | E8: 4 | F8: =INDEX(Daily!$A$3:$A$7964,MATCH(G8,Daily!$C$3:$C$7964,0)) | G8: =SMALL(Daily!$C$3:$C$7964,E8)
A9: 5 | B9: =INDEX(Daily!$A$3:$A$7964,MATCH(C9,Daily!$C$3:$C$7964,0)) | C9: =LARGE(Daily!$C$3:$C$7964,A9) | E9: 5 | F9: =INDEX(Daily!$A$3:$A$7964,MATCH(G9,Daily!$C$3:$C$7964,0)) | G9: =SMALL(Daily!$C$3:$C$7964,E9)
A10: 6 | B10: =INDEX(Daily!$A$3:$A$7964,MATCH(C10,Daily!$C$3:$C$7964,0)) | C10: =LARGE(Daily!$C$3:$C$7964,A10) | E10: 6 | F10: =INDEX(Daily!$A$3:$A$7964,MATCH(G10,Daily!$C$3:$C$7964,0)) | G10: =SMALL(Daily!$C$3:$C$7964,E10)
A11: 7 | B11: =INDEX(Daily!$A$3:$A$7964,MATCH(C11,Daily!$C$3:$C$7964,0)) | C11: =LARGE(Daily!$C$3:$C$7964,A11) | E11: 7 | F11: =INDEX(Daily!$A$3:$A$7964,MATCH(G11,Daily!$C$3:$C$7964,0)) | G11: =SMALL(Daily!$C$3:$C$7964,E11)
A12: 8 | B12: =INDEX(Daily!$A$3:$A$7964,MATCH(C12,Daily!$C$3:$C$7964,0)) | C12: =LARGE(Daily!$C$3:$C$7964,A12) | E12: 8 | F12: =INDEX(Daily!$A$3:$A$7964,MATCH(G12,Daily!$C$3:$C$7964,0)) | G12: =SMALL(Daily!$C$3:$C$7964,E12)
A13: 9 | B13: =INDEX(Daily!$A$3:$A$7964,MATCH(C13,Daily!$C$3:$C$7964,0)) | C13: =LARGE(Daily!$C$3:$C$7964,A13) | E13: 9 | F13: =INDEX(Daily!$A$3:$A$7964,MATCH(G13,Daily!$C$3:$C$7964,0)) | G13: =SMALL(Daily!$C$3:$C$7964,E13)
A14: 10 | B14: =INDEX(Daily!$A$3:$A$7964,MATCH(C14,Daily!$C$3:$C$7964,0)) | C14: =LARGE(Daily!$C$3:$C$7964,A14) | E14: 10 | F14: =INDEX(Daily!$A$3:$A$7964,MATCH(G14,Daily!$C$3:$C$7964,0)) | G14: =SMALL(Daily!$C$3:$C$7964,E14)
A15: 11 | B15: =INDEX(Daily!$A$3:$A$7964,MATCH(C15,Daily!$C$3:$C$7964,0)) | C15: =LARGE(Daily!$C$3:$C$7964,A15) | E15: 11 | F15: =INDEX(Daily!$A$3:$A$7964,MATCH(G15,Daily!$C$3:$C$7964,0)) | G15: =SMALL(Daily!$C$3:$C$7964,E15)
A16: 12 | B16: =INDEX(Daily!$A$3:$A$7964,MATCH(C16,Daily!$C$3:$C$7964,0)) | C16: =LARGE(Daily!$C$3:$C$7964,A16) | E16: 12 | F16: =INDEX(Daily!$A$3:$A$7964,MATCH(G16,Daily!$C$3:$C$7964,0)) | G16: =SMALL(Daily!$C$3:$C$7964,E16)
... A19: 15 | B19: =INDEX(Daily!$A$3:$A$7964,MATCH(C19,Daily!$C$3:$C$7964,0)) | C19: =LARGE(Daily!$C$3:$C$7964,A19) | E19: 15 | F19: =INDEX(Daily!$A$3:$A$7964,MATCH(G19,Daily!$C$3:$C$7964,0)) | G19: =SMALL(Daily!$C$3:$C$7964,E19)

Sheet Methodology
A1: Methodology and sources
A2: Built 2026-10-12 16:35 by krw_fx_monitor.py.
A4: Series | B4: Description | C4: Source used | D4: Obs | E4: First | F4: Last | G4: Note
A5: USD/KRW | B5: KRW per USD, Fed H.10 noon NY buying rate, daily | C5: FRED DEXKOUS | D5: 7963 | E5: 34702 | F5: 46297
A6: USD/JPY | B6: JPY per USD, Fed H.10, daily | C6: FRED DEXJPUS | D6: 7966 | E6: 34702 | F6: 46297
A7: USD/CNY | B7: CNY per USD, Fed H.10, daily | C7: FRED DEXCHUS | D7: 7966 | E7: 34702 | F7: 46297
A8: USD broad | B8: Nominal broad US dollar index (Fed), daily | C8: FRED DTWEXBGS | D8: 5203 | E8: 38719 | F8: 46297
A9: VIX | B9: CBOE VIX, daily close | C9: FRED VIXCLS | D9: 8027 | E9: 34702 | F9: 46303
A10: UST 10Y | B10: US 10-year Treasury yield, %, daily | C10: FRED DGS10 | D10: 7949 | E10: 34702 | F10: 46303
A11: SOFR | B11: Secured overnight financing rate, %, daily | C11: FRED SOFR | D11: 2128 | E11: 43193 | F11: 46303
A12: KRW 3M | B12: Korea 3-month interbank rate, %, monthly (OECD) | C12: FRED IR3TIB01KRM156N | D12: 380 | E12: 34700 | F12: 46235
A13: USD 3M | B13: US 3-month interbank rate, %, monthly (OECD) | C13: FRED IR3TIB01USM156N | D13: 379 | E13: 34700 | F13: 46235
A14: kr_gdp | B14: World Bank NY.GDP.MKTP.KD.ZG (KOR), annual, % | C14: World Bank API NY.GDP.MKTP.KD.ZG | D14: 65 | E14: 1961 | F14: 2025
A15: us_gdp | B15: World Bank NY.GDP.MKTP.KD.ZG (USA), annual, % | C15: World Bank API NY.GDP.MKTP.KD.ZG | D15: 65 | E15: 1961 | F15: 2025
A16: kr_cpi | B16: World Bank FP.CPI.TOTL.ZG (KOR), annual, % | C16: World Bank API FP.CPI.TOTL.ZG | D16: 66 | E16: 1960 | F16: 2025
... A26: BoP pi_l | B26: Portfolio investment, liabilities (inward), US$ mn (matched 'Financial account / Portfolio investment / Portfolio investment, Liabilities') | C26: ECOS 301Y013/BOPF22000000 | D26: 380 | E26: 34700 | F26: 46235
A27: BoP goods | B27: Goods balance | C27: unavailable | D27: 0 | G27: no ECOS item matched
A28: Foreign equity | B28: Foreign investors' net buying, KRW bn, daily (KRX) | C28: KRX via pykrx | D28: 5370 | E28: 38355 | F28: 46307
A30: Colour code: blue = raw data / inputs; black = formulas; green = links to other sheets (shown black on the Dashboard); shaded = overrides.
A31: USD/KRW: Fed H.10 noon New York buying rate. Seoul closing rates (15:30 KST) differ slightly; add an ECOS key for BOK data.
A32: Implied forwards: covered interest parity, KRW ACT/365 and USD ACT/360. Market swap points also reflect the cross-currency basis and dollar funding conditions, so they can differ from rate-implied values.
A33: Monthly 3M rates are OECD interbank series via FRED; they lag and are proxies for desk funding rates. Override on Inputs.
A34: Realized volatility: standard deviation of daily log returns, annualized with the trading-day input.
A35: Macro R²: one-variable fits of Dec-to-Dec log change in USD/KRW on same-year macro gaps. Descriptive, not predictive.
A36: ECOS stat codes used (731Y001/0000001, 817Y002/010502000, 722Y001/0101000) should be checked against the ECOS catalogue; the program skips any series that fails to load.
A37: Flows: monthly balance of payments (BPM6, US$ mn) from Bank of Korea ECOS, items matched by name (see the Series log). Fix a mismatch with flows_config.json, e.g. {"ca": ["301Y013", "000000"]}; list items with --ecos-list 301Y013.
A38: Foreign equity flows: KRX daily net buying by foreign investors (KOSPI + KOSDAQ), via pykrx or your own CSV. Seoul dates; the Daily sheet aligns them to Fed H.10 dates (US holidays drop out), Flows_Daily keeps every Seoul trading day.
A39: Not public: onshore client order flow, exporter forward hedging, offshore NDF positioning, and real-time BOK intervention (disclosed quarterly with a lag).
A40: Not investment advice. Data are provided as published by each source; check critical figures before use.
